{"sheetName":"2023_9_3","totalSongs":241,"lastUpdated":"2026-03-24T09:08:23.401Z","songs":[{"rank":1,"title":"寝起きヤシの木 feat. 歌愛ユキ","artist":"ゆこぴ","englishTitle":"Neoki Yashi no Ki feat. Kaai Yuki","englishArtist":"Yukopi","views":15239004,"viewIncrease":714142,"isOut":false,"isNew":false,"videoId":"FSXsAt7z_RU","videoUrl":"https://youtube.com/watch?v=FSXsAt7z_RU","previousRank":1,"rankChange":0,"changeType":"same","previousWeekViewIncrease":719357},{"rank":2,"title":"デーモンロード feat. 初音ミク","artist":"Kanaria","englishTitle":"Demon Lord feat. Hatsune Miku","englishArtist":"Kanaria","views":8178264,"viewIncrease":257784,"isOut":false,"isNew":false,"videoId":"L5t_TkogtDM","videoUrl":"https://youtube.com/watch?v=L5t_TkogtDM","previousRank":2,"rankChange":0,"changeType":"same","previousWeekViewIncrease":214086},{"rank":3,"title":"人マニア feat. 重音テト","artist":"原口沙輔","englishTitle":"Hito Mania feat. Kasane Teto","englishArtist":"Sasuke Haraguchi","views":991664,"viewIncrease":251061,"isOut":false,"isNew":false,"videoId":"HTxwOxFt5d4","videoUrl":"https://youtube.com/watch?v=HTxwOxFt5d4","previousRank":3,"rankChange":0,"changeType":"same","previousWeekViewIncrease":196142},{"rank":4,"title":"【マジミラ2023】HERO feat. 初音ミク","artist":"Ayase","englishTitle":"【Magical Mirai 2023】HERO","englishArtist":"Ayase","views":3698738,"viewIncrease":166722,"isOut":true,"isNew":false,"videoId":"o4AxMk3SGUY","videoUrl":"https://youtube.com/watch?v=o4AxMk3SGUY","previousRank":4,"rankChange":0,"changeType":"same","previousWeekViewIncrease":164083},{"rank":4,"title":"あいのうた feat. 初音ミク, 重音テト","artist":"大漠波新","englishTitle":"Ai no Uta feat. Hatsune Miku, Kasane Teto","englishArtist":"Daibaku Hashin","views":393830,"viewIncrease":179419,"isOut":false,"isNew":false,"videoId":"LyZk53_5GwM","videoUrl":"https://youtube.com/watch?v=LyZk53_5GwM","previousRank":15,"rankChange":11,"changeType":"up","previousWeekViewIncrease":66969},{"rank":5,"title":"リアライズ feat. 初音ミク","artist":"柊マグネタイト & C'Na","englishTitle":"Realize feat. Hatsune Miku","englishArtist":"Hiiragi Magnetite & C'Na","views":1121837,"viewIncrease":179006,"isOut":false,"isNew":false,"videoId":"pRZwLHrMsvM","videoUrl":"https://youtube.com/watch?v=pRZwLHrMsvM","previousRank":6,"rankChange":1,"changeType":"up","previousWeekViewIncrease":136436},{"rank":6,"title":"あいしていたのに feat. 初音ミク","artist":"MARETU","englishTitle":"Aishiteita no ni feat. Hatsune Miku","englishArtist":"MARETU","views":2707597,"viewIncrease":153240,"isOut":false,"isNew":false,"videoId":"R_g0M5Zmqhg","videoUrl":"https://youtube.com/watch?v=R_g0M5Zmqhg","previousRank":7,"rankChange":1,"changeType":"up","previousWeekViewIncrease":128252},{"rank":7,"title":"リレイアウター feat. 歌愛ユキ","artist":"稲葉曇","englishTitle":"Relay Outer feat. Kaai Yuki","englishArtist":"inabakumori","views":1339627,"viewIncrease":122664,"isOut":false,"isNew":false,"videoId":"b56xjtP6Qac","videoUrl":"https://youtube.com/watch?v=b56xjtP6Qac","previousRank":12,"rankChange":5,"changeType":"up","previousWeekViewIncrease":105918},{"rank":8,"title":"ブループラネット feat. 初音ミク","artist":"DECO*27","englishTitle":"Blue Planet feat. Hatsune Miku","englishArtist":"DECO*27","views":1114609,"viewIncrease":122359,"isOut":false,"isNew":false,"videoId":"-2KzcaiyBFo","videoUrl":"https://youtube.com/watch?v=-2KzcaiyBFo","previousRank":5,"rankChange":-3,"changeType":"down","previousWeekViewIncrease":139257},{"rank":9,"title":"アポカリプスなう feat. 初音ミク","artist":"ピノキオピー","englishTitle":"Apocalypse Now feat. Hatsune Miku","englishArtist":"PinocchioP","views":1287402,"viewIncrease":115788,"isOut":false,"isNew":false,"videoId":"khnNHHGR8jw","videoUrl":"https://youtube.com/watch?v=khnNHHGR8jw","previousRank":11,"rankChange":2,"changeType":"up","previousWeekViewIncrease":113488},{"rank":10,"title":"ミクちゃんのネギネギネギネギ幻騒曲","artist":"Minami no Minami","englishTitle":"Miku-chan no Neginegineginegi Gensou…","englishArtist":"Minami no Minami","views":640423,"viewIncrease":106715,"isOut":false,"isNew":false,"videoId":"357i65-oBY8","videoUrl":"https://youtube.com/watch?v=357i65-oBY8","previousRank":10,"rankChange":0,"changeType":"same","previousWeekViewIncrease":114892},{"rank":11,"title":"演劇 feat. 初音ミク","artist":"ナノウ","englishTitle":"Engeki feat. Hatsune Miku","englishArtist":"nanou","views":1367217,"viewIncrease":92599,"isOut":false,"isNew":false,"videoId":"gJqsFNNCIX0","videoUrl":"https://youtube.com/watch?v=gJqsFNNCIX0","previousRank":13,"rankChange":2,"changeType":"up","previousWeekViewIncrease":79840},{"rank":12,"title":"ギビュリタ feat. グミ","artist":"Vell","englishTitle":"Givurita feat. GUMI","englishArtist":"Vell","views":1284730,"viewIncrease":90999,"isOut":false,"isNew":false,"videoId":"2YjKVSjdDVM","videoUrl":"https://youtube.com/watch?v=2YjKVSjdDVM","previousRank":9,"rankChange":-3,"changeType":"down","previousWeekViewIncrease":119164},{"rank":13,"title":"そのまんまそのまんま、そのままずっとそのまま","artist":"きくお","englishTitle":"Sono Manma Sono Manma, Sono Mama…","englishArtist":"Kikuo","views":570045,"viewIncrease":77753,"isOut":false,"isNew":false,"videoId":"CwP1pT6aDcM","videoUrl":"https://youtube.com/watch?v=CwP1pT6aDcM","previousRank":14,"rankChange":1,"changeType":"up","previousWeekViewIncrease":70583},{"rank":14,"title":"BLINDNESS feat. 初音ミク","artist":"john","englishTitle":"BLINDNESS feat. Hatsune Miku","englishArtist":"john","views":195121,"viewIncrease":75476,"isOut":false,"isNew":false,"videoId":"vOyl7a9zAG0","videoUrl":"https://youtube.com/watch?v=vOyl7a9zAG0","previousRank":8,"rankChange":-6,"changeType":"down","previousWeekViewIncrease":119645},{"rank":15,"title":"ずんだシェイキング","artist":"なみぐる","englishTitle":"Zunda Shaking","englishArtist":"namigroove","views":658062,"viewIncrease":74786,"isOut":false,"isNew":false,"videoId":"DVSlQuF0Pcg","videoUrl":"https://youtube.com/watch?v=DVSlQuF0Pcg","previousRank":16,"rankChange":1,"changeType":"up","previousWeekViewIncrease":66271},{"rank":16,"title":"プロポーズ feat. 可不","artist":"内緒のピアス","englishTitle":"Propose feat. KAFU","englishArtist":"Naisho no Pierce","views":1132306,"viewIncrease":66793,"isOut":false,"isNew":false,"videoId":"ST_AJmY_Tcc","videoUrl":"https://youtube.com/watch?v=ST_AJmY_Tcc","previousRank":18,"rankChange":2,"changeType":"up","previousWeekViewIncrease":50897},{"rank":17,"title":"下剋上 feat.可不","artist":"Misumi","englishTitle":"Gekokujou feat. KAFU","englishArtist":"Misumi","views":92950,"viewIncrease":63831,"isOut":false,"isNew":false,"videoId":"akO2mUie1Ds","videoUrl":"https://youtube.com/watch?v=akO2mUie1Ds","previousRank":30,"rankChange":13,"changeType":"up","previousWeekViewIncrease":29119},{"rank":18,"title":"マザーグーグー feat. ユウマ","artist":"柊キライ","englishTitle":"Mother Gu Gu feat. Yuma","englishArtist":"Hiiragi Kirai","views":55722,"viewIncrease":55722,"isOut":false,"isNew":true,"videoId":"ZFc4zO2oSiA","videoUrl":"https://youtube.com/watch?v=ZFc4zO2oSiA","rankChange":null,"changeType":"new","previousWeekViewIncrease":0},{"rank":19,"title":"チャンネル登録よろしくお願いします","artist":"GYARI","englishTitle":"Channel​ Touroku Yoroshiku Onegaishimasu","englishArtist":"GYARI","views":832008,"viewIncrease":52524,"isOut":false,"isNew":false,"videoId":"BbyqEMSDuww","videoUrl":"https://youtube.com/watch?v=BbyqEMSDuww","previousRank":19,"rankChange":0,"changeType":"same","previousWeekViewIncrease":50887},{"rank":20,"title":"転生したら可愛かった feat. 可不","artist":"Kaoru","englishTitle":"Tensei shitara kawaikatta feat. KAFU","englishArtist":"Kaoru","views":556412,"viewIncrease":47262,"isOut":false,"isNew":false,"videoId":"SulrbQm2xLo","videoUrl":"https://youtube.com/watch?v=SulrbQm2xLo","previousRank":17,"rankChange":-3,"changeType":"down","previousWeekViewIncrease":57719},{"rank":21,"title":"教育教育教育教育死刑死刑死刑教育教育教育教育","artist":"もやしさらだ","englishTitle":"KyoikuKyoikuKyouikuKyouikuShikeiShikei…","englishArtist":"moyasisarada","views":1593619,"viewIncrease":47102,"isOut":false,"isNew":false,"videoId":"UUi6mPLlGH0","videoUrl":"https://youtube.com/watch?v=UUi6mPLlGH0","previousRank":20,"rankChange":-1,"changeType":"down","previousWeekViewIncrease":42626},{"rank":22,"title":"ミィハー feat. 重音テト","artist":"ちのぞー","englishTitle":"follower of the crowd feat. Kasane Teto","englishArtist":"Chinozo","views":1392852,"viewIncrease":46448,"isOut":false,"isNew":false,"videoId":"oePX92KTE_M","videoUrl":"https://youtube.com/watch?v=oePX92KTE_M","previousRank":21,"rankChange":-1,"changeType":"down","previousWeekViewIncrease":41117},{"rank":23,"title":"魔天楼 feat. flower","artist":"煮ル果実","englishTitle":"Matenrou feat. v flower","englishArtist":"NILFRUITS","views":427702,"viewIncrease":35604,"isOut":false,"isNew":false,"videoId":"90ue3buf9Tw","videoUrl":"https://youtube.com/watch?v=90ue3buf9Tw","previousRank":25,"rankChange":2,"changeType":"up","previousWeekViewIncrease":32329},{"rank":24,"title":"ヘヴンリーユー feat. りむる","artist":"ろねぴ","englishTitle":"Heavenly You feat. Rimuru","englishArtist":"LonePi","views":187352,"viewIncrease":35300,"isOut":false,"isNew":false,"videoId":"tR15E2QD63U","videoUrl":"https://youtube.com/watch?v=tR15E2QD63U","previousRank":29,"rankChange":5,"changeType":"up","previousWeekViewIncrease":29688},{"rank":25,"title":"キラピピ★キラピカ","artist":"nyanyannya","englishTitle":"Kirapipi★Kirapika","englishArtist":"nyanyannya","views":302047,"viewIncrease":34613,"isOut":false,"isNew":false,"videoId":"mQH0Fmk1K0g","videoUrl":"https://youtube.com/watch?v=mQH0Fmk1K0g","previousRank":24,"rankChange":-1,"changeType":"down","previousWeekViewIncrease":35184},{"rank":26,"title":"ちっちゃな私 feat. 重音テト","artist":"マサラダ","englishTitle":"Chiccha na Watashi feat. Kasane Teto","englishArtist":"Masarada","views":319967,"viewIncrease":34425,"isOut":false,"isNew":false,"videoId":"4aFC2oC-wHA","videoUrl":"https://youtube.com/watch?v=4aFC2oC-wHA","previousRank":27,"rankChange":1,"changeType":"up","previousWeekViewIncrease":30896},{"rank":27,"title":"モア！ジャンプ！モア！ feat. 初音ミク","artist":"Nayutalien","englishTitle":"More! Jump! More! feat. Hatsune Miku","englishArtist":"Nayutalien","views":884086,"viewIncrease":33659,"isOut":false,"isNew":false,"videoId":"jwZWhMnSvm4","videoUrl":"https://youtube.com/watch?v=jwZWhMnSvm4","previousRank":26,"rankChange":-1,"changeType":"down","previousWeekViewIncrease":31786},{"rank":28,"title":"ボイドロイド feat. 羽累, miku, una","artist":"r-906","englishTitle":"voidroid feat. HARU, miku, una","englishArtist":"r-906","views":253477,"viewIncrease":33258,"isOut":false,"isNew":false,"videoId":"KhmFHCivKOc","videoUrl":"https://youtube.com/watch?v=KhmFHCivKOc","previousRank":28,"rankChange":0,"changeType":"same","previousWeekViewIncrease":30693},{"rank":29,"title":"リビド feat. Ci flower","artist":"john","englishTitle":"Libido feat. Ci flower","englishArtist":"john","views":33063,"viewIncrease":33063,"isOut":false,"isNew":true,"videoId":"jhFqV3THf5s","videoUrl":"https://youtube.com/watch?v=jhFqV3THf5s","rankChange":null,"changeType":"new","previousWeekViewIncrease":0},{"rank":30,"title":"怪電話 feat. ROSE & POPY","artist":"r-906","englishTitle":"A mysterious phone call","englishArtist":"r-906","views":331355,"viewIncrease":29789,"isOut":false,"isNew":false,"videoId":"zh7ihYKaqYs","videoUrl":"https://youtube.com/watch?v=zh7ihYKaqYs","previousRank":33,"rankChange":3,"changeType":"up","previousWeekViewIncrease":26958},{"rank":31,"title":"混沌ブギ feat. 初音ミク","artist":"jon-YAKITORY","englishTitle":"Konton Boogie feat. Hatsune Miku","englishArtist":"jon-YAKITORY","views":141008,"viewIncrease":29630,"isOut":false,"isNew":false,"videoId":"1Swg-aBO9eY","videoUrl":"https://youtube.com/watch?v=1Swg-aBO9eY","previousRank":23,"rankChange":-8,"changeType":"down","previousWeekViewIncrease":36032},{"rank":32,"title":"ブーケガルニ feat. Flower","artist":"煮ル果実","englishTitle":"Bouquet Garni feat. flower","englishArtist":"NILFRUITS","views":666307,"viewIncrease":29097,"isOut":false,"isNew":false,"videoId":"4FmE4tva0tU","videoUrl":"https://youtube.com/watch?v=4FmE4tva0tU","previousRank":38,"rankChange":6,"changeType":"up","previousWeekViewIncrease":24761},{"rank":33,"title":"サヨナラ！！ウイルス feat. 初音ミク","artist":"キュー","englishTitle":"Sayonara!! Virus feat. Hatsune Miku","englishArtist":"Kyuu","views":178673,"viewIncrease":29046,"isOut":false,"isNew":false,"videoId":"1VvkM2T4uWU","videoUrl":"https://youtube.com/watch?v=1VvkM2T4uWU","previousRank":37,"rankChange":4,"changeType":"up","previousWeekViewIncrease":24983},{"rank":34,"title":"宇宙散歩 feat. 初音ミク","artist":"DECO*27","englishTitle":"Cosmic Rendezvous feat. Hatsune Miku","englishArtist":"DECO*27","views":1144657,"viewIncrease":28975,"isOut":false,"isNew":false,"videoId":"M4B-k4aPx58","videoUrl":"https://youtube.com/watch?v=M4B-k4aPx58","previousRank":35,"rankChange":1,"changeType":"up","previousWeekViewIncrease":26321},{"rank":35,"title":"トゥー・ユー・グリーンライツ feat. 初音ミク","artist":"Omoi","englishTitle":"To You Greenlights feat. Hatsune Miku","englishArtist":"Omoi","views":814411,"viewIncrease":28267,"isOut":false,"isNew":false,"videoId":"FWPkzDMUitg","videoUrl":"https://youtube.com/watch?v=FWPkzDMUitg","previousRank":31,"rankChange":-4,"changeType":"down","previousWeekViewIncrease":28112},{"rank":36,"title":"アタシ×I×MY∴理想論 / 初音ミク","artist":"ユリイ・カノン","englishTitle":"Atashi×I×MY∴Risouron / Hatsune Miku","englishArtist":"Yurry Canon","views":682781,"viewIncrease":27409,"isOut":false,"isNew":false,"videoId":"k2CO3gJTnYE","videoUrl":"https://youtube.com/watch?v=k2CO3gJTnYE","previousRank":32,"rankChange":-4,"changeType":"down","previousWeekViewIncrease":27106},{"rank":37,"title":"風呂入るプロファイル feat. 初音ミク","artist":"もちうつね","englishTitle":"Furo Hairu Profile feat. Hatsune Miku","englishArtist":"mochiutsune","views":291741,"viewIncrease":27003,"isOut":false,"isNew":false,"videoId":"010nHWXwdYw","videoUrl":"https://youtube.com/watch?v=010nHWXwdYw","previousRank":39,"rankChange":2,"changeType":"up","previousWeekViewIncrease":24647},{"rank":38,"title":"ただ病名が欲しかった feat. 可不, 星界, カゼヒキ","artist":"きぃく","englishTitle":"Just wanted a name for the disease","englishArtist":"kyiku","views":25915,"viewIncrease":25915,"isOut":false,"isNew":true,"videoId":"FSLxRRQdNs4","videoUrl":"https://youtube.com/watch?v=FSLxRRQdNs4","rankChange":null,"changeType":"new","previousWeekViewIncrease":0},{"rank":39,"title":"なぁぜなぁぜ？なぁぜなぁぜ？なぁぜなぁぜ？…","artist":"もやしさらだ","englishTitle":"Naaze Naaze? Naaze Naaze? Naaze Naaze?...","englishArtist":"moyasisarada","views":291115,"viewIncrease":25723,"isOut":false,"isNew":false,"videoId":"l9CxfswKKZ8","videoUrl":"https://youtube.com/watch?v=l9CxfswKKZ8","previousRank":50,"rankChange":11,"changeType":"up","previousWeekViewIncrease":16524},{"rank":40,"title":"おどロボ","artist":"海茶","englishTitle":"Odorobo","englishArtist":"Umicha","views":243472,"viewIncrease":24474,"isOut":false,"isNew":false,"videoId":"D_UC0WJmLnc","videoUrl":"https://youtube.com/watch?v=D_UC0WJmLnc","previousRank":43,"rankChange":3,"changeType":"up","previousWeekViewIncrease":21490},{"rank":41,"title":"ロースピードフェイクリリック feat. 羽累","artist":"cosMo@暴走P","englishTitle":"LowSpeed Fake Lyric feat. HARU","englishArtist":"cosMo","views":610540,"viewIncrease":24433,"isOut":false,"isNew":false,"videoId":"5bDI_ZgAIDw","videoUrl":"https://youtube.com/watch?v=5bDI_ZgAIDw","previousRank":42,"rankChange":1,"changeType":"up","previousWeekViewIncrease":21941},{"rank":42,"title":"死ンデレラ feat. 初音ミク","artist":"mitsu_akuma","englishTitle":"Cinder Girl feat. Hatsune Miku","englishArtist":"mitsu_akuma","views":62735,"viewIncrease":23900,"isOut":false,"isNew":false,"videoId":"3EEHSIlkWis","videoUrl":"https://youtube.com/watch?v=3EEHSIlkWis","previousRank":22,"rankChange":-20,"changeType":"down","previousWeekViewIncrease":38835},{"rank":43,"title":"キューピット feat. 初音ミク","artist":"Kai","englishTitle":"Cupid feat. Hatsune Miku","englishArtist":"Kai","views":228617,"viewIncrease":21962,"isOut":false,"isNew":false,"videoId":"XHeqXQjAGYU","videoUrl":"https://youtube.com/watch?v=XHeqXQjAGYU","previousRank":44,"rankChange":1,"changeType":"up","previousWeekViewIncrease":21049},{"rank":44,"title":"フィオーレ feat. 初音ミク, 可不","artist":"MIMI","englishTitle":"Fiore​ feat. Hatsune Miku, KAFU","englishArtist":"MIMI","views":163467,"viewIncrease":21152,"isOut":false,"isNew":false,"videoId":"xgNeFTCzpgo","videoUrl":"https://youtube.com/watch?v=xgNeFTCzpgo","previousRank":47,"rankChange":3,"changeType":"up","previousWeekViewIncrease":20069},{"rank":45,"title":"エモーショナルドットネット feat. りむる","artist":"Frog96","englishTitle":"Emotional Dot Net feat. Rimuru","englishArtist":"Frog96","views":216171,"viewIncrease":20884,"isOut":false,"isNew":false,"videoId":"YX34bTLNDdM","videoUrl":"https://youtube.com/watch?v=YX34bTLNDdM","previousRank":46,"rankChange":1,"changeType":"up","previousWeekViewIncrease":20582},{"rank":46,"title":"マンハッタン feat. MEIKO","artist":"wotaku","englishTitle":"Manhattan feat. MEIKO","englishArtist":"wotaku","views":208756,"viewIncrease":19053,"isOut":false,"isNew":false,"videoId":"D4OzAM7DjUM","videoUrl":"https://youtube.com/watch?v=D4OzAM7DjUM","previousRank":34,"rankChange":-12,"changeType":"down","previousWeekViewIncrease":26821},{"rank":47,"title":"イワユル天使 feat. 初音ミク","artist":"Vell","englishTitle":"Iwayuru Tenshi feat. Hatsune Miku","englishArtist":"Vell","views":18951,"viewIncrease":18951,"isOut":false,"isNew":true,"videoId":"p0jegI_xXaY","videoUrl":"https://youtube.com/watch?v=p0jegI_xXaY","rankChange":null,"changeType":"new","previousWeekViewIncrease":0},{"rank":48,"title":"マミー feat. v flower","artist":"レディモス","englishTitle":"Mummy feat. v flower","englishArtist":"LadyMonsters.","views":18688,"viewIncrease":18688,"isOut":false,"isNew":true,"videoId":"jHbcu6udmI0","videoUrl":"https://youtube.com/watch?v=jHbcu6udmI0","rankChange":null,"changeType":"new","previousWeekViewIncrease":0},{"rank":49,"title":"チームメイト feat. 初音ミク","artist":"HoneyWorks","englishTitle":"Teammate feat. Hatsune Miku","englishArtist":"HoneyWorks","views":678991,"viewIncrease":18921,"isOut":true,"isNew":false,"videoId":"QAbwPeAYf_o","videoUrl":"https://youtube.com/watch?v=QAbwPeAYf_o","previousRank":49,"rankChange":0,"changeType":"same","previousWeekViewIncrease":16739},{"rank":49,"title":"すれちがいわづらひ feat. 初音ミク","artist":"ナナエム","englishTitle":"Surechigaiwa Zura Hi feat. Hatsune Miku","englishArtist":"Nanaemu","views":204860,"viewIncrease":18120,"isOut":false,"isNew":false,"videoId":"rwmdS-_1rUw","videoUrl":"https://youtube.com/watch?v=rwmdS-_1rUw","previousRank":40,"rankChange":-9,"changeType":"down","previousWeekViewIncrease":23136},{"rank":50,"title":"アルマニ feat. 初音ミク","artist":"ざんぎ / Zangi","englishTitle":"Almani feat. Hatsune Miku","englishArtist":"Zangi","views":90515,"viewIncrease":17796,"isOut":false,"isNew":false,"videoId":"w6uJC2WtREY","videoUrl":"https://youtube.com/watch?v=w6uJC2WtREY","previousRank":52,"rankChange":2,"changeType":"up","previousWeekViewIncrease":15713},{"rank":51,"title":"ファンタズマ feat. 初音ミク","artist":"sasakure.UK","englishTitle":"Phantasma feat. Hatsune Miku","englishArtist":"sasakure.UK","views":274726,"viewIncrease":17502,"isOut":false,"isNew":false,"videoId":"mNq4xWsRsT0","videoUrl":"https://youtube.com/watch?v=mNq4xWsRsT0","previousRank":51,"rankChange":0,"changeType":"same","previousWeekViewIncrease":16064},{"rank":52,"title":"コアラ feat. VY1","artist":"Will Stetson","englishTitle":"Koala feat. VY1","englishArtist":"Will Stetson","views":153039,"viewIncrease":16413,"isOut":false,"isNew":false,"videoId":"oYXRTijfLfg","videoUrl":"https://youtube.com/watch?v=oYXRTijfLfg","previousRank":41,"rankChange":-11,"changeType":"down","previousWeekViewIncrease":23065},{"rank":53,"title":"巫 feat. 羽累","artist":"柊マグネタイト","englishTitle":"Miko feat. HARU","englishArtist":"Hiiragi Magnetite","views":267188,"viewIncrease":16285,"isOut":false,"isNew":false,"videoId":"KTKpgpW3HTw","videoUrl":"https://youtube.com/watch?v=KTKpgpW3HTw","previousRank":53,"rankChange":0,"changeType":"same","previousWeekViewIncrease":15313},{"rank":54,"title":"ねむれわたがし feat. 花奏かのんβ","artist":"一二三","englishTitle":"Go To Sleep, Cotton Candy feat. Kanade Kanonβ","englishArtist":"Hifumi","views":15259,"viewIncrease":15259,"isOut":false,"isNew":true,"videoId":"CaeSu7L1XqY","videoUrl":"https://youtube.com/watch?v=CaeSu7L1XqY","rankChange":null,"changeType":"new","previousWeekViewIncrease":0},{"rank":55,"title":"ワールド・ランプシェード [reunion]","artist":"buzzG","englishTitle":"World Lampshade [reunion] feat. GUMI","englishArtist":"buzzG","views":43264,"viewIncrease":14825,"isOut":false,"isNew":false,"videoId":"my5jUzXag3k","videoUrl":"https://youtube.com/watch?v=my5jUzXag3k","previousRank":45,"rankChange":-10,"changeType":"down","previousWeekViewIncrease":20873},{"rank":56,"title":"G戦上のカリギュラ feat. 初音ミク","artist":"ナナエム","englishTitle":"Caligula on the G Line feat. Hatsune Miku","englishArtist":"Nanaemu","views":516874,"viewIncrease":14163,"isOut":false,"isNew":false,"videoId":"f8E8toxEFW0","videoUrl":"https://youtube.com/watch?v=f8E8toxEFW0","previousRank":57,"rankChange":1,"changeType":"up","previousWeekViewIncrease":13557},{"rank":57,"title":"ラブレター feat. 初音ミク","artist":"傘村トータ","englishTitle":"Love Letter feat. Hatsune Miku","englishArtist":"Kasamura Tota","views":270687,"viewIncrease":13940,"isOut":false,"isNew":false,"videoId":"p0UjmYJ9sfw","videoUrl":"https://youtube.com/watch?v=p0UjmYJ9sfw","previousRank":58,"rankChange":1,"changeType":"up","previousWeekViewIncrease":13381},{"rank":58,"title":"パキパキ天使のハードラック feat. りむる","artist":"捨て垢","englishTitle":"Paki Paki Tenshi no Hard Luck feat. Rimuru","englishArtist":"STEAKA","views":125633,"viewIncrease":13503,"isOut":false,"isNew":false,"videoId":"xXpCzMDJkik","videoUrl":"https://youtube.com/watch?v=xXpCzMDJkik","previousRank":59,"rankChange":1,"changeType":"up","previousWeekViewIncrease":12855},{"rank":59,"title":"やめてください feat. 羽累","artist":"柊マグネタイト","englishTitle":"Yamete Kudasai feat. HARU","englishArtist":"Hiiragi Magnetite","views":555114,"viewIncrease":13307,"isOut":false,"isNew":false,"videoId":"JijOz4Rvzn8","videoUrl":"https://youtube.com/watch?v=JijOz4Rvzn8","previousRank":55,"rankChange":-4,"changeType":"down","previousWeekViewIncrease":13884},{"rank":60,"title":"バッドエンドメーカー feat. りむる","artist":"香椎モイミ","englishTitle":"Bad End Maker feat. Rimuru","englishArtist":"Kashii Moimi","views":93583,"viewIncrease":12657,"isOut":false,"isNew":false,"videoId":"9C8ASbkd5no","videoUrl":"https://youtube.com/watch?v=9C8ASbkd5no","previousRank":54,"rankChange":-6,"changeType":"down","previousWeekViewIncrease":14630},{"rank":61,"title":"天才 feat. 巡音ルカ","artist":"奏音69","englishTitle":"Tensai feat. Megurine Luka","englishArtist":"KANON69","views":131496,"viewIncrease":12455,"isOut":false,"isNew":false,"videoId":"8j5iyrDKHwk","videoUrl":"https://youtube.com/watch?v=8j5iyrDKHwk","previousRank":48,"rankChange":-13,"changeType":"down","previousWeekViewIncrease":17530},{"rank":62,"title":"イントゥ・ナイトメア","artist":"ユリイ・カノン","englishTitle":"Into Nightmare","englishArtist":"YurryCanon","views":156985,"viewIncrease":12353,"isOut":false,"isNew":false,"videoId":"ftku1SyJCtg","videoUrl":"https://youtube.com/watch?v=ftku1SyJCtg","previousRank":61,"rankChange":-1,"changeType":"down","previousWeekViewIncrease":10626},{"rank":63,"title":"バンビ feat. 裏命","artist":"WONDERFUL★OPPORTUNITY!","englishTitle":"Bambi feat. RIME","englishArtist":"WONDERFUL★OPPORTUNITY!","views":42647,"viewIncrease":10838,"isOut":false,"isNew":false,"videoId":"6VljfKhzcV4","videoUrl":"https://youtube.com/watch?v=6VljfKhzcV4","previousRank":36,"rankChange":-27,"changeType":"down","previousWeekViewIncrease":25121},{"rank":64,"title":"キスしちゃだめっ！ feat. 可不","artist":"HoneyWorks","englishTitle":"No kissing! feat. KAFU","englishArtist":"HoneyWorks","views":363006,"viewIncrease":9654,"isOut":true,"isNew":false,"videoId":"a-t0jwon7_E","videoUrl":"https://youtube.com/watch?v=a-t0jwon7_E","previousRank":64,"rankChange":0,"changeType":"same","previousWeekViewIncrease":9690},{"rank":64,"title":"コウフク貯金 feat. 初音ミク","artist":"MIMI","englishTitle":"Koufuku Chokin feat. Hatsune Miku","englishArtist":"MIMI","views":214404,"viewIncrease":10290,"isOut":false,"isNew":false,"videoId":"zQqIm-EVlkQ","videoUrl":"https://youtube.com/watch?v=zQqIm-EVlkQ","previousRank":62,"rankChange":-2,"changeType":"down","previousWeekViewIncrease":10596},{"rank":65,"title":"グリーディン feat. Flower","artist":"Hiiragi Kirai","englishTitle":"Greedin feat. Flower","englishArtist":"Hiiragi Kirai","views":158107,"viewIncrease":9861,"isOut":false,"isNew":false,"videoId":"4jRwzUa5bvA","videoUrl":"https://youtube.com/watch?v=4jRwzUa5bvA","previousRank":68,"rankChange":3,"changeType":"up","previousWeekViewIncrease":8377},{"rank":66,"title":"キングスレイヤー feat. 初音ミク","artist":"マイキP","englishTitle":"King Slayer feat. Hatsune Miku","englishArtist":"Maiki P","views":72768,"viewIncrease":9830,"isOut":false,"isNew":false,"videoId":"PFjBXaTSpRg","videoUrl":"https://youtube.com/watch?v=PFjBXaTSpRg","previousRank":56,"rankChange":-10,"changeType":"down","previousWeekViewIncrease":13681},{"rank":67,"title":"Be with Master feat. 初音ミク","artist":"ラマーズP","englishTitle":"Be with Master feat. Hatsune Miku","englishArtist":"LamazeP","views":75134,"viewIncrease":9698,"isOut":false,"isNew":false,"videoId":"ZwMvF-PnUFc","videoUrl":"https://youtube.com/watch?v=ZwMvF-PnUFc","previousRank":60,"rankChange":-7,"changeType":"down","previousWeekViewIncrease":11523},{"rank":68,"title":"OSINT feat. 結月ゆかり, 重音テト, 歌愛ユキ","artist":"椎乃味醂","englishTitle":"OSINT","englishArtist":"sheeno mirin","views":109380,"viewIncrease":9535,"isOut":false,"isNew":false,"videoId":"N9gQqOf58mQ","videoUrl":"https://youtube.com/watch?v=N9gQqOf58mQ","previousRank":67,"rankChange":-1,"changeType":"down","previousWeekViewIncrease":8758},{"rank":69,"title":"Parasite feat. 羽累, Bonbero","artist":"r-906","englishTitle":"Parasite feat. HARU, Bonbero","englishArtist":"r-906","views":95859,"viewIncrease":9270,"isOut":false,"isNew":false,"videoId":"ThfAX20n0pA","videoUrl":"https://youtube.com/watch?v=ThfAX20n0pA","previousRank":66,"rankChange":-3,"changeType":"down","previousWeekViewIncrease":9060},{"rank":70,"title":"ジャックポットヤミー feat. 初音ミク","artist":"Vell","englishTitle":"Jackpot Yummy feat. Hatsune Miku","englishArtist":"Vell","views":310819,"viewIncrease":9126,"isOut":false,"isNew":false,"videoId":"SWaR1EUWu_4","videoUrl":"https://youtube.com/watch?v=SWaR1EUWu_4","previousRank":70,"rankChange":0,"changeType":"same","previousWeekViewIncrease":8254},{"rank":71,"title":"下品 feat. flower","artist":"鬱P","englishTitle":"Vulgar feat. flower","englishArtist":"Utsu-P","views":260982,"viewIncrease":8998,"isOut":false,"isNew":false,"videoId":"5sKwaCeWm3w","videoUrl":"https://youtube.com/watch?v=5sKwaCeWm3w","previousRank":80,"rankChange":9,"changeType":"up","previousWeekViewIncrease":7050},{"rank":72,"title":"紫色の向日葵 feat. 羽累","artist":"香椎モイミ","englishTitle":"Murasakiiro no Himawari feat. HARU","englishArtist":"Kashii Moimi","views":160694,"viewIncrease":8884,"isOut":false,"isNew":false,"videoId":"lp-dv1Tb1KI","videoUrl":"https://youtube.com/watch?v=lp-dv1Tb1KI","previousRank":69,"rankChange":-3,"changeType":"down","previousWeekViewIncrease":8289},{"rank":73,"title":"轆轤首 feat. Flower","artist":"レディモス","englishTitle":"Rokurokubi feat. flower","englishArtist":"LadyMonsters.","views":127124,"viewIncrease":8693,"isOut":false,"isNew":false,"videoId":"7I7w6lk8fWY","videoUrl":"https://youtube.com/watch?v=7I7w6lk8fWY","previousRank":84,"rankChange":11,"changeType":"up","previousWeekViewIncrease":6358},{"rank":74,"title":"息をするだけ feat. 可不","artist":"MIMI","englishTitle":"Iki o suru dake feat. KAFU","englishArtist":"MIMI","views":186954,"viewIncrease":8613,"isOut":false,"isNew":false,"videoId":"ArqagB9P1Qs","videoUrl":"https://youtube.com/watch?v=ArqagB9P1Qs","previousRank":77,"rankChange":3,"changeType":"up","previousWeekViewIncrease":7488},{"rank":75,"title":"万物流転 feat. Flower","artist":"ぬゆり","englishTitle":"Banbutsu Ruten feat. v flower","englishArtist":"nulut","views":123947,"viewIncrease":8563,"isOut":false,"isNew":false,"videoId":"lFdg21FN0A0","videoUrl":"https://youtube.com/watch?v=lFdg21FN0A0","previousRank":63,"rankChange":-12,"changeType":"down","previousWeekViewIncrease":10296},{"rank":76,"title":"Dead or Like feat. 初音ミク","artist":"Dyes Iwasaki","englishTitle":"Dead or Like feat. Hatsune Miku","englishArtist":"Dyes Iwasaki","views":143006,"viewIncrease":8402,"isOut":false,"isNew":false,"videoId":"6sVzV2tTpcs","videoUrl":"https://youtube.com/watch?v=6sVzV2tTpcs","previousRank":74,"rankChange":-2,"changeType":"down","previousWeekViewIncrease":7806},{"rank":77,"title":"UNDERST按D feat. 初音ミク","artist":"梅とら","englishTitle":"UNDERSTAND feat. Hatsune Miku","englishArtist":"Umetora","views":8337,"viewIncrease":8337,"isOut":false,"isNew":true,"videoId":"piITWALODR8","videoUrl":"https://youtube.com/watch?v=piITWALODR8","rankChange":null,"changeType":"new","previousWeekViewIncrease":0},{"rank":78,"title":"文化になっていく feat. 初音ミク","artist":"カンザキイオリ","englishTitle":"Bunka ni Natte iku feat. Hatsune Miku","englishArtist":"Kanzaki Iori","views":150609,"viewIncrease":8247,"isOut":false,"isNew":false,"videoId":"t4olLwsyWSg","videoUrl":"https://youtube.com/watch?v=t4olLwsyWSg","previousRank":71,"rankChange":-7,"changeType":"down","previousWeekViewIncrease":8195},{"rank":79,"title":"もっとはやくそれになりたい！ feat. 音街ウナ","artist":"キノシタ","englishTitle":"Motto Hayaku Sore ni Naritai!","englishArtist":"Kinoshita","views":190418,"viewIncrease":8194,"isOut":false,"isNew":false,"videoId":"gq6HBtPzSgU","videoUrl":"https://youtube.com/watch?v=gq6HBtPzSgU","previousRank":73,"rankChange":-6,"changeType":"down","previousWeekViewIncrease":7992},{"rank":80,"title":"詩ニ花 feat. 初音ミク","artist":"雨ノ漣","englishTitle":"Shi ni Hana feat. Hatsune Miku","englishArtist":"Ame no Sazanami","views":12834,"viewIncrease":7477,"isOut":false,"isNew":false,"videoId":"V8fM4lJ9hbM","videoUrl":"https://youtube.com/watch?v=V8fM4lJ9hbM","previousRank":90,"rankChange":10,"changeType":"up","previousWeekViewIncrease":5357},{"rank":81,"title":"オーバーロード feat. 初音ミク","artist":"ふぁるすてぃ","englishTitle":"Overload feat. Hatsune Miku","englishArtist":"fallstay","views":67551,"viewIncrease":7467,"isOut":false,"isNew":false,"videoId":"172ol54StE0","videoUrl":"https://youtube.com/watch?v=172ol54StE0","previousRank":79,"rankChange":-2,"changeType":"down","previousWeekViewIncrease":7314},{"rank":82,"title":"ゴールデンレイ feat. 初音ミク","artist":"Harumaki Gohan","englishTitle":"Golden Ray feat. Hatsune Miku","englishArtist":"Harumaki Gohan","views":222637,"viewIncrease":6647,"isOut":false,"isNew":false,"videoId":"yBaC3IfbK2M","videoUrl":"https://youtube.com/watch?v=yBaC3IfbK2M","previousRank":92,"rankChange":10,"changeType":"up","previousWeekViewIncrease":5112},{"rank":83,"title":"やったれ！音合戦 feat. 初音ミク","artist":"まらしぃ","englishTitle":"Yattare! Otogassen feat. Hatsune Miku","englishArtist":"marasy","views":104602,"viewIncrease":6443,"isOut":false,"isNew":false,"videoId":"vsbaSbm09SM","videoUrl":"https://youtube.com/watch?v=vsbaSbm09SM","previousRank":78,"rankChange":-5,"changeType":"down","previousWeekViewIncrease":7424},{"rank":84,"title":"Saloon feat. 羽累","artist":"R Sound Design","englishTitle":"Saloon feat. HARU","englishArtist":"R Sound Design","views":92589,"viewIncrease":6397,"isOut":false,"isNew":false,"videoId":"zEezpM56vYU","videoUrl":"https://youtube.com/watch?v=zEezpM56vYU","previousRank":82,"rankChange":-2,"changeType":"down","previousWeekViewIncrease":6657},{"rank":85,"title":"嘶く feat. 裏命","artist":"西沢さんP","englishTitle":"inanaku feat. RIME","englishArtist":"NishizawasanP","views":62875,"viewIncrease":6360,"isOut":false,"isNew":false,"videoId":"IBrLzvFIx6Y","videoUrl":"https://youtube.com/watch?v=IBrLzvFIx6Y","previousRank":85,"rankChange":0,"changeType":"same","previousWeekViewIncrease":6288},{"rank":86,"title":"C.A.／旭音エマ","artist":"アボガド6","englishTitle":"C.A.／Asane Ema","englishArtist":"avogado6","views":96555,"viewIncrease":6349,"isOut":false,"isNew":false,"videoId":"oqIJdgmFTTY","videoUrl":"https://youtube.com/watch?v=oqIJdgmFTTY","previousRank":72,"rankChange":-14,"changeType":"down","previousWeekViewIncrease":8010},{"rank":87,"title":"ジェニ feat. flower","artist":"和田志文","englishTitle":"Jeni feat. flower","englishArtist":"¿?shimon","views":425114,"viewIncrease":7056,"isOut":true,"isNew":false,"videoId":"rZToN-L9HRs","videoUrl":"https://youtube.com/watch?v=rZToN-L9HRs","previousRank":87,"rankChange":0,"changeType":"same","previousWeekViewIncrease":6015},{"rank":87,"title":"WE ARE HATSUNE MIKU","artist":"BIGHEAD","englishTitle":"WE ARE HATSUNE MIKU","englishArtist":"BIGHEAD","views":68029,"viewIncrease":6289,"isOut":false,"isNew":false,"videoId":"yORGvNLyrr0","videoUrl":"https://youtube.com/watch?v=yORGvNLyrr0","previousRank":94,"rankChange":7,"changeType":"up","previousWeekViewIncrease":4854},{"rank":88,"title":"MAZE feat. 鏡音リン","artist":"Noz.","englishTitle":"MAZE feat. Kagamine Rin","englishArtist":"Noz.","views":77605,"viewIncrease":6248,"isOut":false,"isNew":false,"videoId":"c3BtQQleevo","videoUrl":"https://youtube.com/watch?v=c3BtQQleevo","previousRank":83,"rankChange":-5,"changeType":"down","previousWeekViewIncrease":6383},{"rank":89,"title":"レトロイド feat. 杏戸ゆげβ","artist":"じゃんきー","englishTitle":"Retroid feat. And Ugeβ","englishArtist":"Junky","views":6157,"viewIncrease":6157,"isOut":false,"isNew":true,"videoId":"PVaWaIB5l0s","videoUrl":"https://youtube.com/watch?v=PVaWaIB5l0s","rankChange":null,"changeType":"new","previousWeekViewIncrease":0},{"rank":90,"title":"大作戦です。 feat. 裏命","artist":"A4。","englishTitle":"Great Strategy. feat. RIME","englishArtist":"A4。","views":6040,"viewIncrease":6040,"isOut":false,"isNew":true,"videoId":"_AKTKW0eoCA","videoUrl":"https://youtube.com/watch?v=_AKTKW0eoCA","rankChange":null,"changeType":"new","previousWeekViewIncrease":0},{"rank":91,"title":"ブルベ、恋をする feat. 初音ミク","artist":"R Sound Design","englishTitle":"Burube, Koi o Suru feat. Hatsune Miku","englishArtist":"R Sound Design","views":218567,"viewIncrease":5858,"isOut":false,"isNew":false,"videoId":"HPfURUnV3Oo","videoUrl":"https://youtube.com/watch?v=HPfURUnV3Oo","previousRank":86,"rankChange":-5,"changeType":"down","previousWeekViewIncrease":6241},{"rank":92,"title":"あなたのうた feat. 羽累","artist":"一二三","englishTitle":"Anata no Uta feat. HARU","englishArtist":"Hifumi","views":49581,"viewIncrease":5756,"isOut":false,"isNew":false,"videoId":"UiKbpdPnGhA","videoUrl":"https://youtube.com/watch?v=UiKbpdPnGhA","previousRank":81,"rankChange":-11,"changeType":"down","previousWeekViewIncrease":6987},{"rank":93,"title":"星を繋ぐ feat. 初音ミク","artist":"40mP x 一二三","englishTitle":"Hoshi wo Tsunagu feat. Hatsune Miku","englishArtist":"40mP x Hifumi","views":161039,"viewIncrease":5689,"isOut":false,"isNew":false,"videoId":"Fo3qg44Rn6Q","videoUrl":"https://youtube.com/watch?v=Fo3qg44Rn6Q","previousRank":95,"rankChange":2,"changeType":"up","previousWeekViewIncrease":4765},{"rank":94,"title":"Mystic Parade feat. 鏡音リン, 鏡音レン","artist":"ひとしずく×やま△","englishTitle":"Mystic Parade feat. Kagamine Rin, Len","englishArtist":"Hitoshizuku×Yama△","views":137891,"viewIncrease":5622,"isOut":false,"isNew":false,"videoId":"cw3PDnpjp8Q","videoUrl":"https://youtube.com/watch?v=cw3PDnpjp8Q","previousRank":98,"rankChange":4,"changeType":"up","previousWeekViewIncrease":4456},{"rank":95,"title":"ムチャプリンセス feat. りむる","artist":"Meddmia","englishTitle":"Mucha Princess feat. Rimuru","englishArtist":"Meddmia","views":59444,"viewIncrease":5615,"isOut":false,"isNew":false,"videoId":"pgb_2wFcpuU","videoUrl":"https://youtube.com/watch?v=pgb_2wFcpuU","previousRank":89,"rankChange":-6,"changeType":"down","previousWeekViewIncrease":5449},{"rank":96,"title":"ghost feat. 裏命","artist":"ぐいあの","englishTitle":"ghost feat. RIME","englishArtist":"Guiano","views":187643,"viewIncrease":5496,"isOut":false,"isNew":false,"videoId":"upUv8iWVs-I","videoUrl":"https://youtube.com/watch?v=upUv8iWVs-I","previousRank":93,"rankChange":-3,"changeType":"down","previousWeekViewIncrease":4959},{"rank":97,"title":"悠久休暇","artist":"halyosy","englishTitle":"Eternal Vacation","englishArtist":"halyosy","views":214490,"viewIncrease":5220,"isOut":false,"isNew":false,"videoId":"JLa8FvQf_RA","videoUrl":"https://youtube.com/watch?v=JLa8FvQf_RA","previousRank":88,"rankChange":-9,"changeType":"down","previousWeekViewIncrease":5686},{"rank":98,"title":"YOU feat. 初音ミク","artist":"JUVENILE","englishTitle":"YOU feat. Hatsune Miku","englishArtist":"JUVENILE","views":52945,"viewIncrease":4750,"isOut":false,"isNew":false,"videoId":"O6tiC2jiXKg","videoUrl":"https://youtube.com/watch?v=O6tiC2jiXKg","previousRank":107,"rankChange":9,"changeType":"up","previousWeekViewIncrease":3830},{"rank":99,"title":"だらだらたれる feat. ミテ","artist":"__","englishTitle":"Daradara Tareru feat. Mite","englishArtist":"__","views":12031,"viewIncrease":4396,"isOut":false,"isNew":false,"videoId":"woU_5j39Lgw","videoUrl":"https://youtube.com/watch?v=woU_5j39Lgw","previousRank":76,"rankChange":-23,"changeType":"down","previousWeekViewIncrease":7635},{"rank":100,"title":"まわる洗濯ネット feat. 足立レイ","artist":"ピクド","englishTitle":"Mawaru Sentaku Net feat. Adachi Rei","englishArtist":"picdo","views":54279,"viewIncrease":4372,"isOut":false,"isNew":false,"videoId":"6Qmuqihcr5E","videoUrl":"https://youtube.com/watch?v=6Qmuqihcr5E","previousRank":99,"rankChange":-1,"changeType":"down","previousWeekViewIncrease":4363},{"rank":101,"title":"幽光、1/fのゆらめき feat. 初音ミク","artist":"卯花ロク","englishTitle":"Yuukou, 1/f no Yurameki feat. Hatsune Miku","englishArtist":"Uka Roku","views":45435,"viewIncrease":4307,"isOut":false,"isNew":false,"videoId":"ZynP9ajVfuI","videoUrl":"https://youtube.com/watch?v=ZynP9ajVfuI","previousRank":104,"rankChange":3,"changeType":"up","previousWeekViewIncrease":3970},{"rank":102,"title":"Un‐Lock feat. 巡音ルカ","artist":"Powerless","englishTitle":"Un‐Lock feat. Megurine Luka","englishArtist":"Powerless","views":4208,"viewIncrease":4208,"isOut":false,"isNew":true,"videoId":"cdw_2hCSYys","videoUrl":"https://youtube.com/watch?v=cdw_2hCSYys","rankChange":null,"changeType":"new","previousWeekViewIncrease":0},{"rank":103,"title":"夜祭 feat. 可不","artist":"てにをは","englishTitle":"Yomatsuri feat. KAFU","englishArtist":"Teniwoha","views":91494,"viewIncrease":4106,"isOut":false,"isNew":false,"videoId":"VSHzeauAwaI","videoUrl":"https://youtube.com/watch?v=VSHzeauAwaI","previousRank":102,"rankChange":-1,"changeType":"down","previousWeekViewIncrease":4098},{"rank":104,"title":"ゼーレ feat. 可不&羽累","artist":"hiroki.","englishTitle":"Seele feat.KAFU&HARU","englishArtist":"hiroki.","views":4550,"viewIncrease":4047,"isOut":false,"isNew":false,"videoId":"1N7mSq0iWkk","videoUrl":"https://youtube.com/watch?v=1N7mSq0iWkk","previousRank":172,"rankChange":68,"changeType":"up","previousWeekViewIncrease":503},{"rank":105,"title":"ファーストラスト feat. 初音ミク","artist":"せきこみごはん","englishTitle":"First Last feat. Hatsune Miku","englishArtist":"Sekikomi Gohan","views":25200,"viewIncrease":3931,"isOut":false,"isNew":false,"videoId":"7kmVYwNr_Ig","videoUrl":"https://youtube.com/watch?v=7kmVYwNr_Ig","previousRank":100,"rankChange":-5,"changeType":"down","previousWeekViewIncrease":4323},{"rank":106,"title":"【鏡音リンレン】悪きっず","artist":"WONDERFUL★OPPORTUNITY!","englishTitle":"【Kagamine Rin, Len】WARU KIDS","englishArtist":"WONDERFUL★OPPORTUNITY!","views":63993,"viewIncrease":3800,"isOut":false,"isNew":false,"videoId":"Lybv7qTHsG8","videoUrl":"https://youtube.com/watch?v=Lybv7qTHsG8","previousRank":103,"rankChange":-3,"changeType":"down","previousWeekViewIncrease":4060},{"rank":107,"title":"being loved feat. 歌愛ユキ","artist":"えもん","englishTitle":"being loved feat. Kaai Yuki","englishArtist":"Emon","views":156210,"viewIncrease":3713,"isOut":false,"isNew":false,"videoId":"HD9G6GoH15E","videoUrl":"https://youtube.com/watch?v=HD9G6GoH15E","previousRank":101,"rankChange":-6,"changeType":"down","previousWeekViewIncrease":4126},{"rank":108,"title":"黎明のネオンサイン feat. 初音ミク","artist":"豆カカオ","englishTitle":"Reimei no Neon Sign feat. Hatsune Miku","englishArtist":"Mame Kakao","views":13144,"viewIncrease":3663,"isOut":false,"isNew":false,"videoId":"686kH_Y1TAY","videoUrl":"https://youtube.com/watch?v=686kH_Y1TAY","previousRank":65,"rankChange":-43,"changeType":"down","previousWeekViewIncrease":9481},{"rank":109,"title":"タワーマンション feat. 根音ネネ","artist":"atokata","englishTitle":"Tower Mansion feat. Nene Nene","englishArtist":"atokata","views":15489,"viewIncrease":3534,"isOut":false,"isNew":false,"videoId":"LtPfsky_iKM","videoUrl":"https://youtube.com/watch?v=LtPfsky_iKM","previousRank":131,"rankChange":22,"changeType":"up","previousWeekViewIncrease":1742},{"rank":110,"title":"イリア feat. 可不","artist":"ぬゆり","englishTitle":"Iria feat. KAFU","englishArtist":"nulut","views":172143,"viewIncrease":3505,"isOut":false,"isNew":false,"videoId":"ex99ewtdCeE","videoUrl":"https://youtube.com/watch?v=ex99ewtdCeE","previousRank":106,"rankChange":-4,"changeType":"down","previousWeekViewIncrease":3902},{"rank":111,"title":"僕は依存症 feat. 裏命","artist":"みきとP","englishTitle":"I am Dependant feat. RIME","englishArtist":"MikitoP","views":232587,"viewIncrease":3461,"isOut":false,"isNew":false,"videoId":"tsmoGglN91Q","videoUrl":"https://youtube.com/watch?v=tsmoGglN91Q","previousRank":112,"rankChange":1,"changeType":"up","previousWeekViewIncrease":2986},{"rank":112,"title":"どっちなんだ！ feat. 音街ウナ","artist":"和田たけあき","englishTitle":"Docchi nanda! feat. Otomachi Una","englishArtist":"WADATAKEAKI","views":134879,"viewIncrease":3404,"isOut":false,"isNew":false,"videoId":"AjQAMx3WRgw","videoUrl":"https://youtube.com/watch?v=AjQAMx3WRgw","previousRank":113,"rankChange":1,"changeType":"up","previousWeekViewIncrease":2977},{"rank":113,"title":"心のない歌 feat. 初音ミク","artist":"真島ゆろ","englishTitle":"Kokoro no Nai Uta feat. Hatsune Miku","englishArtist":"yuro mashima","views":30937,"viewIncrease":3198,"isOut":false,"isNew":false,"videoId":"AxcSKptPXsA","videoUrl":"https://youtube.com/watch?v=AxcSKptPXsA","previousRank":105,"rankChange":-8,"changeType":"down","previousWeekViewIncrease":3921},{"rank":114,"title":"-New stories- feat. 初音ミク","artist":"OSTER project","englishTitle":"-New stories- feat. Hatsune Miku","englishArtist":"OSTER project","views":60279,"viewIncrease":3126,"isOut":false,"isNew":false,"videoId":"t4kLzpzaEeQ","videoUrl":"https://youtube.com/watch?v=t4kLzpzaEeQ","previousRank":121,"rankChange":7,"changeType":"up","previousWeekViewIncrease":2404},{"rank":115,"title":"その兎はいつまでも楽しみにしていたお茶会。","artist":"Haniwa","englishTitle":"Sono Usagi wa Itsumademo Tanoshimi ni Shi…","englishArtist":"Haniwa","views":91507,"viewIncrease":3126,"isOut":false,"isNew":false,"videoId":"GVaMFzYC02A","videoUrl":"https://youtube.com/watch?v=GVaMFzYC02A","previousRank":118,"rankChange":3,"changeType":"up","previousWeekViewIncrease":2657},{"rank":116,"title":"我らステインバスターズ！ feat. 鏡音リン, 初音ミク","artist":"真島ゆろ","englishTitle":"Warera Stain Busters!","englishArtist":"Mashima Yuro","views":124474,"viewIncrease":3108,"isOut":false,"isNew":false,"videoId":"OOQWSLYx1u0","videoUrl":"https://youtube.com/watch?v=OOQWSLYx1u0","previousRank":114,"rankChange":-2,"changeType":"down","previousWeekViewIncrease":2955},{"rank":117,"title":"目に緋色 feat. 初音ミク","artist":"獅子志司","englishTitle":"Me ni Hiiro feat. Hatsune Miku","englishArtist":"Shishi Shishi","views":45233,"viewIncrease":3033,"isOut":false,"isNew":false,"videoId":"G6azqC91xqE","videoUrl":"https://youtube.com/watch?v=G6azqC91xqE","previousRank":109,"rankChange":-8,"changeType":"down","previousWeekViewIncrease":3200},{"rank":118,"title":"ぐるぐるつづく feat. ミテ","artist":"__","englishTitle":"Guruguru Tsuzuku feat. Mite","englishArtist":"__","views":19222,"viewIncrease":2968,"isOut":false,"isNew":false,"videoId":"7evB2Js-Y-8","videoUrl":"https://youtube.com/watch?v=7evB2Js-Y-8","previousRank":97,"rankChange":-21,"changeType":"down","previousWeekViewIncrease":4578},{"rank":119,"title":"あまもや feat. 裏命, 狐子","artist":"r-906","englishTitle":"Amamoya feat. RIME, COKO","englishArtist":"r-906","views":97124,"viewIncrease":2903,"isOut":false,"isNew":false,"videoId":"_mQb6EELl-Y","videoUrl":"https://youtube.com/watch?v=_mQb6EELl-Y","previousRank":116,"rankChange":-3,"changeType":"down","previousWeekViewIncrease":2811},{"rank":120,"title":"Re:SectionIV feat. 初音ミク","artist":"R Sound Design","englishTitle":"Re:SectionIV feat. Hatsune Miku","englishArtist":"R Sound Design","views":32038,"viewIncrease":2835,"isOut":false,"isNew":false,"videoId":"GPgtvGzLAq0","videoUrl":"https://youtube.com/watch?v=GPgtvGzLAq0","previousRank":110,"rankChange":-10,"changeType":"down","previousWeekViewIncrease":3196},{"rank":121,"title":"女の子になっちゃう！ feat. 初音ミク","artist":"ラマーズP","englishTitle":"Onna no Ko ni Nacchau! feat. Hatsune Miku","englishArtist":"LamazeP","views":49150,"viewIncrease":2696,"isOut":false,"isNew":false,"videoId":"dmpRcX07HLM","videoUrl":"https://youtube.com/watch?v=dmpRcX07HLM","previousRank":115,"rankChange":-6,"changeType":"down","previousWeekViewIncrease":2945},{"rank":122,"title":"られへんわ feat. 鏡音リン, 鏡音レン","artist":"ワンダフル★オポチュニティ！","englishTitle":"Rarehen wa feat. Kagamine Rin, Len","englishArtist":"WONDERFUL★OPPORTUNITY!","views":212130,"viewIncrease":2695,"isOut":false,"isNew":false,"videoId":"w8ZG26wgjgM","videoUrl":"https://youtube.com/watch?v=w8ZG26wgjgM","previousRank":117,"rankChange":-5,"changeType":"down","previousWeekViewIncrease":2704},{"rank":123,"title":"カンフーが足りてない。feat. 夏色花梨","artist":"A Ghostly Tale","englishTitle":"Not enough kung fu feat. Natsuki Karin","englishArtist":"A Ghostly Tale","views":5481,"viewIncrease":2634,"isOut":false,"isNew":false,"videoId":"UYAXIZSfsF0","videoUrl":"https://youtube.com/watch?v=UYAXIZSfsF0","previousRank":125,"rankChange":2,"changeType":"up","previousWeekViewIncrease":2061},{"rank":124,"title":"ゴーストライター feat. MYK-IV","artist":"マイキP","englishTitle":"Ghost Writer feat. MYK-IV","englishArtist":"Maiki P","views":69717,"viewIncrease":2510,"isOut":false,"isNew":false,"videoId":"0jOGbltlC2Q","videoUrl":"https://youtube.com/watch?v=0jOGbltlC2Q","previousRank":122,"rankChange":-2,"changeType":"down","previousWeekViewIncrease":2175},{"rank":125,"title":"ルナ / 初音ミク","artist":"Aliey:S","englishTitle":"Luna feat. Hatsune Miku","englishArtist":"Aliey:S","views":7768,"viewIncrease":2472,"isOut":false,"isNew":false,"videoId":"7c_-czkgZ1g","videoUrl":"https://youtube.com/watch?v=7c_-czkgZ1g","previousRank":136,"rankChange":11,"changeType":"up","previousWeekViewIncrease":1427},{"rank":126,"title":"MIKU BREAK NOW feat. 初音ミク","artist":"BIGHEAD","englishTitle":"MIKU BREAK NOW feat. Hatsune Miku","englishArtist":"BIGHEAD","views":44483,"viewIncrease":2329,"isOut":false,"isNew":false,"videoId":"GI7MhZRTxwM","videoUrl":"https://youtube.com/watch?v=GI7MhZRTxwM","previousRank":126,"rankChange":0,"changeType":"same","previousWeekViewIncrease":1958},{"rank":127,"title":"籠鳥ループ feat. 初音ミク","artist":"枝","englishTitle":"Rouchou Loop feat. Hatsune Miku","englishArtist":"Eda","views":4847,"viewIncrease":2271,"isOut":false,"isNew":false,"videoId":"ZCIbkP1_3tk","videoUrl":"https://youtube.com/watch?v=ZCIbkP1_3tk","previousRank":119,"rankChange":-8,"changeType":"down","previousWeekViewIncrease":2576},{"rank":128,"title":"終末期 feat. 星界","artist":"FILEIN","englishTitle":"Terminal Stage feat. SEKAI","englishArtist":"FILEIN","views":27030,"viewIncrease":2227,"isOut":false,"isNew":false,"videoId":"4fW3EnMKxDY","videoUrl":"https://youtube.com/watch?v=4fW3EnMKxDY","previousRank":124,"rankChange":-4,"changeType":"down","previousWeekViewIncrease":2101},{"rank":129,"title":"Lemonade feat. 初音ミク","artist":"wotaku","englishTitle":"Lemonade feat. Hatsune Miku","englishArtist":"wotaku","views":132344,"viewIncrease":2017,"isOut":false,"isNew":false,"videoId":"sL9pwTK-LEU","videoUrl":"https://youtube.com/watch?v=sL9pwTK-LEU","previousRank":127,"rankChange":-2,"changeType":"down","previousWeekViewIncrease":1924},{"rank":130,"title":"メロウライト","artist":"まらしぃ×のう","englishTitle":"Mellow Light","englishArtist":"marasy×Nou","views":117167,"viewIncrease":1947,"isOut":false,"isNew":false,"videoId":"vG8--B9-5fY","videoUrl":"https://youtube.com/watch?v=vG8--B9-5fY","previousRank":75,"rankChange":-55,"changeType":"down","previousWeekViewIncrease":7695},{"rank":131,"title":"フレイラヴィランゼ feat. 鳴花ミコト","artist":"ユギカ","englishTitle":"FrailL'aVillanos feat. Meika Mikoto","englishArtist":"Yugika","views":24376,"viewIncrease":1933,"isOut":false,"isNew":false,"videoId":"9VDY3lbpK90","videoUrl":"https://youtube.com/watch?v=9VDY3lbpK90","previousRank":130,"rankChange":-1,"changeType":"down","previousWeekViewIncrease":1748},{"rank":132,"title":"コイフルヨル feat. 初音ミク","artist":"あまね","englishTitle":"Koifuru Yoru feat. Hatsune Miku","englishArtist":"Amane","views":5270,"viewIncrease":1931,"isOut":false,"isNew":false,"videoId":"m3N9unM_JOY","videoUrl":"https://youtube.com/watch?v=m3N9unM_JOY","previousRank":108,"rankChange":-24,"changeType":"down","previousWeekViewIncrease":3339},{"rank":133,"title":"I素U feat. 初音ミク","artist":"大漠波新","englishTitle":"I So U feat. Hatsune Miku","englishArtist":"Daibaku Hashin","views":27423,"viewIncrease":1927,"isOut":false,"isNew":false,"videoId":"c5foJsjkMV4","videoUrl":"https://youtube.com/watch?v=c5foJsjkMV4","previousRank":139,"rankChange":6,"changeType":"up","previousWeekViewIncrease":1342},{"rank":134,"title":"Nobody & Anyone feat. 初音ミク","artist":"KENGO","englishTitle":"Nobody & Anyone feat. Hatsune Miku","englishArtist":"KENGO","views":30469,"viewIncrease":1912,"isOut":false,"isNew":false,"videoId":"t8uFi8PTyvg","videoUrl":"https://youtube.com/watch?v=t8uFi8PTyvg","previousRank":135,"rankChange":1,"changeType":"up","previousWeekViewIncrease":1437},{"rank":135,"title":"ココロノメロディー feat. Mai","artist":"Rulicapim","englishTitle":"Kokoro no Melody feat. Mai","englishArtist":"Rulicapim","views":1829,"viewIncrease":1829,"isOut":false,"isNew":true,"videoId":"xoKLqY9_JkQ","videoUrl":"https://youtube.com/watch?v=xoKLqY9_JkQ","rankChange":null,"changeType":"new","previousWeekViewIncrease":0},{"rank":136,"title":"ぜろぐらむ feat. 星界","artist":"みきとP","englishTitle":"zerogram feat. SEKAI","englishArtist":"MikitoP","views":36625,"viewIncrease":1804,"isOut":false,"isNew":false,"videoId":"j1cdr2dkGVs","videoUrl":"https://youtube.com/watch?v=j1cdr2dkGVs","previousRank":128,"rankChange":-8,"changeType":"down","previousWeekViewIncrease":1910},{"rank":137,"title":"愛してるときは同じ言葉で feat. 初音ミク","artist":"えいぐふと","englishTitle":"Itoshiteru Toki wa Onaji Kotoba de","englishArtist":"Eiguft","views":4750,"viewIncrease":1612,"isOut":false,"isNew":false,"videoId":"uvqh6oILBDs","videoUrl":"https://youtube.com/watch?v=uvqh6oILBDs","previousRank":111,"rankChange":-26,"changeType":"down","previousWeekViewIncrease":3138},{"rank":138,"title":"バックファイア feat. 羽累","artist":"ぐちり","englishTitle":"Back Fire feat. HARU","englishArtist":"Guchiry","views":35137,"viewIncrease":1452,"isOut":false,"isNew":false,"videoId":"5L0jcPn6rsQ","videoUrl":"https://youtube.com/watch?v=5L0jcPn6rsQ","previousRank":146,"rankChange":8,"changeType":"up","previousWeekViewIncrease":1163},{"rank":139,"title":"1212。feat.可不","artist":"エイハブ X A4。","englishTitle":"1212。feat.KAFU","englishArtist":"AHUB X A4。","views":34695,"viewIncrease":1427,"isOut":false,"isNew":false,"videoId":"9ZL98c6ytxA","videoUrl":"https://youtube.com/watch?v=9ZL98c6ytxA","previousRank":141,"rankChange":2,"changeType":"up","previousWeekViewIncrease":1292},{"rank":140,"title":"ぎみぎみ、えぶりしんぐ！ feat. 初音ミク","artist":"卯花ロク","englishTitle":"GimiGimi, Everything! feat. Hatsune Miku","englishArtist":"ukaroku","views":6113,"viewIncrease":1379,"isOut":false,"isNew":false,"videoId":"qtZhsueFfpY","videoUrl":"https://youtube.com/watch?v=qtZhsueFfpY","previousRank":96,"rankChange":-44,"changeType":"down","previousWeekViewIncrease":4734},{"rank":141,"title":"HIGHWAY STAR feat. 初音ミク","artist":"大漠波新","englishTitle":"HIGHWAY STAR feat. Hatsune Miku","englishArtist":"Daibaku Hashin","views":12822,"viewIncrease":1355,"isOut":false,"isNew":false,"videoId":"IjngoOnwF0I","videoUrl":"https://youtube.com/watch?v=IjngoOnwF0I","previousRank":155,"rankChange":14,"changeType":"up","previousWeekViewIncrease":845},{"rank":142,"title":"ヴァイパーヴァイパー feat. りむる","artist":"Fushi","englishTitle":"Viper Viper feat. Rimuru","englishArtist":"Fushi","views":15068,"viewIncrease":1346,"isOut":false,"isNew":false,"videoId":"5A7hlbLnnqI","videoUrl":"https://youtube.com/watch?v=5A7hlbLnnqI","previousRank":134,"rankChange":-8,"changeType":"down","previousWeekViewIncrease":1439},{"rank":143,"title":"Cool Me Down feat. 巡音ルカ","artist":"Mwk","englishTitle":"Cool Me Down feat. Megurine Luka","englishArtist":"Mwk","views":20786,"viewIncrease":1331,"isOut":false,"isNew":false,"videoId":"57sE6RAFerk","videoUrl":"https://youtube.com/watch?v=57sE6RAFerk","previousRank":144,"rankChange":1,"changeType":"up","previousWeekViewIncrease":1201},{"rank":144,"title":"シアワセバニー feat. 初音ミク","artist":"氷東","englishTitle":"Shiawase Bunny feat. Hatsune Miku","englishArtist":"Hyoudou","views":30800,"viewIncrease":1287,"isOut":false,"isNew":false,"videoId":"b48yiqMPAvM","videoUrl":"https://youtube.com/watch?v=b48yiqMPAvM","previousRank":138,"rankChange":-6,"changeType":"down","previousWeekViewIncrease":1349},{"rank":145,"title":"なにがレトロブームじゃい feat. 桜乃そら","artist":"mustie=DC","englishTitle":"Nani ga Retro Boom jai feat. Haruno Sora","englishArtist":"mustie=DC","views":22496,"viewIncrease":1271,"isOut":false,"isNew":false,"videoId":"w0Auikms4NE","videoUrl":"https://youtube.com/watch?v=w0Auikms4NE","previousRank":145,"rankChange":0,"changeType":"same","previousWeekViewIncrease":1187},{"rank":146,"title":"ブレス・ユー feat. カゼヒキβ","artist":"是","englishTitle":"Bless You feat. Kazehikiβ","englishArtist":"ze","views":13899,"viewIncrease":1264,"isOut":false,"isNew":false,"videoId":"XDXAvTks4E0","videoUrl":"https://youtube.com/watch?v=XDXAvTks4E0","previousRank":140,"rankChange":-6,"changeType":"down","previousWeekViewIncrease":1338},{"rank":147,"title":"エンドコンテンツ feat. 可不","artist":"GaL","englishTitle":"End Content feat. KAFU","englishArtist":"GaL","views":3095,"viewIncrease":1263,"isOut":false,"isNew":false,"videoId":"7EXq8DOF9pc","videoUrl":"https://youtube.com/watch?v=7EXq8DOF9pc","previousRank":129,"rankChange":-18,"changeType":"down","previousWeekViewIncrease":1832},{"rank":148,"title":"百花繚乱☆スターマイン","artist":"雪乃イト","englishTitle":"Hyakkaryouran☆Starmine","englishArtist":"Yukino Ito","views":75631,"viewIncrease":1219,"isOut":false,"isNew":false,"videoId":"mPEQTkacBls","videoUrl":"https://youtube.com/watch?v=mPEQTkacBls","previousRank":91,"rankChange":-57,"changeType":"down","previousWeekViewIncrease":5357},{"rank":149,"title":"コーリー feat. 初音ミク","artist":"雨ノ漣","englishTitle":"Cory feat. Hatsune Miku","englishArtist":"Ame no Sazanami","views":24442,"viewIncrease":1167,"isOut":false,"isNew":false,"videoId":"RbKB60CjcZY","videoUrl":"https://youtube.com/watch?v=RbKB60CjcZY","previousRank":143,"rankChange":-6,"changeType":"down","previousWeekViewIncrease":1214},{"rank":150,"title":"地下に埋まる橋架とあおでんわ feat. 重音テト","artist":"すずぬい","englishTitle":"The bridge and the blue phone under the…","englishArtist":"Suzunui","views":9788,"viewIncrease":923,"isOut":false,"isNew":false,"videoId":"Q5pTiRxlFSA","videoUrl":"https://youtube.com/watch?v=Q5pTiRxlFSA","previousRank":150,"rankChange":0,"changeType":"same","previousWeekViewIncrease":943},{"rank":151,"title":"ハートエンディング feat. ゲキヤクβ","artist":"てづ","englishTitle":"Heart Ending feat. Gekiyakuβ","englishArtist":"Tezu","views":2520,"viewIncrease":912,"isOut":false,"isNew":false,"videoId":"d3ptx4xUgzw","videoUrl":"https://youtube.com/watch?v=d3ptx4xUgzw","previousRank":132,"rankChange":-19,"changeType":"down","previousWeekViewIncrease":1608},{"rank":152,"title":"雨はヤだね feat. 歌愛ユキ","artist":"ヒロモトヒライシン","englishTitle":"Ame wa Yadane feat. Kaai Yuki","englishArtist":"Hiromoto Hiraishin","views":1847,"viewIncrease":877,"isOut":false,"isNew":false,"videoId":"Kmea1FP83Pw","videoUrl":"https://youtube.com/watch?v=Kmea1FP83Pw","previousRank":148,"rankChange":-4,"changeType":"down","previousWeekViewIncrease":970},{"rank":153,"title":"とまらない！ feat. 初音ミク","artist":"B9P","englishTitle":"Tomaranai! feat. Hatsune Miku","englishArtist":"B9P","views":872,"viewIncrease":872,"isOut":false,"isNew":true,"videoId":"kEu6SqHsIVA","videoUrl":"https://youtube.com/watch?v=kEu6SqHsIVA","rankChange":null,"changeType":"new","previousWeekViewIncrease":0},{"rank":154,"title":"きさらぎ後進曲  feat. MEIKO","artist":"惑井","englishTitle":"Kisaragi Koushinkyouku feat. MEIKO","englishArtist":"Madoi","views":3144,"viewIncrease":857,"isOut":false,"isNew":false,"videoId":"kK2ToyY7q_Y","videoUrl":"https://youtube.com/watch?v=kK2ToyY7q_Y","previousRank":133,"rankChange":-21,"changeType":"down","previousWeekViewIncrease":1464},{"rank":155,"title":"まどろむスタディ feat. 星尘Infinity","artist":"キツネリ","englishTitle":"Madoromu Study feat. Xingchen Infinity","englishArtist":"Kitsuneri","views":9956,"viewIncrease":814,"isOut":false,"isNew":false,"videoId":"fxDSINwG8To","videoUrl":"https://youtube.com/watch?v=fxDSINwG8To","previousRank":151,"rankChange":-4,"changeType":"down","previousWeekViewIncrease":925},{"rank":156,"title":"フールフールフール feat. 初音ミク","artist":"ゆきChii","englishTitle":"Fool, Fool, Fool feat. Hatsune Miku","englishArtist":"YukiChii","views":800,"viewIncrease":800,"isOut":false,"isNew":true,"videoId":"LU4qyQIg5rw","videoUrl":"https://youtube.com/watch?v=LU4qyQIg5rw","rankChange":null,"changeType":"new","previousWeekViewIncrease":0},{"rank":157,"title":"Jack In The Box feat. 初音ミク","artist":"唐紅","englishTitle":"Jack In The Box feat. Hatsune Miku","englishArtist":"Karakurenai","views":23832,"viewIncrease":793,"isOut":false,"isNew":false,"videoId":"KEOz9TRQHfw","videoUrl":"https://youtube.com/watch?v=KEOz9TRQHfw","previousRank":164,"rankChange":7,"changeType":"up","previousWeekViewIncrease":621},{"rank":158,"title":"リデッドストック feat. 鳴花ミコト","artist":"ユギカ","englishTitle":"ReDeadStock feat. Meika Mikoto","englishArtist":"Yugika","views":24338,"viewIncrease":787,"isOut":false,"isNew":false,"videoId":"B7xCnzt1kaY","videoUrl":"https://youtube.com/watch?v=B7xCnzt1kaY","previousRank":162,"rankChange":4,"changeType":"up","previousWeekViewIncrease":651},{"rank":159,"title":"ないたーないたー feat. 初音ミク","artist":"雨ノ漣","englishTitle":"Nighter Nighter feat. Hatsune Miku","englishArtist":"Ame no Sazanami","views":29762,"viewIncrease":786,"isOut":false,"isNew":false,"videoId":"DmaNtJvYfP4","videoUrl":"https://youtube.com/watch?v=DmaNtJvYfP4","previousRank":156,"rankChange":-3,"changeType":"down","previousWeekViewIncrease":831},{"rank":160,"title":"ポップス・ネヴァー・ダイ feat. 巡音ルカ","artist":"Shu","englishTitle":"Pops Never Die feat. Megurine Luka","englishArtist":"Shu","views":772,"viewIncrease":772,"isOut":false,"isNew":true,"videoId":"t2R3sAqIUZA","videoUrl":"https://youtube.com/watch?v=t2R3sAqIUZA","rankChange":null,"changeType":"new","previousWeekViewIncrease":0},{"rank":161,"title":"レーザービィム feat. 初音ミク","artist":"呆","englishTitle":"Laser Beam feat. Hatsune Miku","englishArtist":"Akire","views":5995,"viewIncrease":736,"isOut":false,"isNew":false,"videoId":"gWamfcW_04Q","videoUrl":"https://youtube.com/watch?v=gWamfcW_04Q","previousRank":149,"rankChange":-12,"changeType":"down","previousWeekViewIncrease":950},{"rank":162,"title":"九夏 feat. 浮遊レイ","artist":"rinri","englishTitle":"Kyuuka feat. Fuyuu Rei","englishArtist":"rinri","views":11716,"viewIncrease":731,"isOut":false,"isNew":false,"videoId":"Zwb_vfkJB4A","videoUrl":"https://youtube.com/watch?v=Zwb_vfkJB4A","previousRank":161,"rankChange":-1,"changeType":"down","previousWeekViewIncrease":696},{"rank":163,"title":"青春ハイウェイ feat. 初音ミク","artist":"はるな","englishTitle":"Seishun Highway feat. Hatsune Miku","englishArtist":"haruna","views":5137,"viewIncrease":704,"isOut":false,"isNew":false,"videoId":"bSpFJTJ2QDU","videoUrl":"https://youtube.com/watch?v=bSpFJTJ2QDU","previousRank":147,"rankChange":-16,"changeType":"down","previousWeekViewIncrease":1007},{"rank":164,"title":"いっぱいキャパシティ","artist":"宮守文学","englishTitle":"Ippai Capacity","englishArtist":"Miyamori Bungaku","views":6976,"viewIncrease":664,"isOut":false,"isNew":false,"videoId":"BiiuxgAIghI","videoUrl":"https://youtube.com/watch?v=BiiuxgAIghI","previousRank":166,"rankChange":2,"changeType":"up","previousWeekViewIncrease":562},{"rank":165,"title":"バブル feat. 初音ミク, ナースロボ＿タイプＴ","artist":"higma","englishTitle":"Bubble","englishArtist":"higma","views":26833,"viewIncrease":643,"isOut":false,"isNew":false,"videoId":"Gd4eR3jYCdc","videoUrl":"https://youtube.com/watch?v=Gd4eR3jYCdc","previousRank":165,"rankChange":0,"changeType":"same","previousWeekViewIncrease":620},{"rank":166,"title":"バニタ feat. v flower","artist":"駱駝法師","englishTitle":"B U R N I T U P feat. v flower","englishArtist":"Rakuda Boushi","views":1420,"viewIncrease":635,"isOut":false,"isNew":false,"videoId":"Qjx2ilr6kbQ","videoUrl":"https://youtube.com/watch?v=Qjx2ilr6kbQ","previousRank":157,"rankChange":-9,"changeType":"down","previousWeekViewIncrease":785},{"rank":167,"title":"夏空ノスタルジー feat. 夏色花梨","artist":"雪乃イト","englishTitle":"Natsuzora Nostalgia feat. Natsuki Karin","englishArtist":"Yukino Ito","views":17920,"viewIncrease":606,"isOut":false,"isNew":false,"videoId":"zK65j3lJ1tI","videoUrl":"https://youtube.com/watch?v=zK65j3lJ1tI","previousRank":160,"rankChange":-7,"changeType":"down","previousWeekViewIncrease":698},{"rank":168,"title":"いらんこ憂鬱 feat. 初音ミク","artist":"Amu","englishTitle":"Iranko Melancholy feat. Hatsune Miku","englishArtist":"Amu","views":10047,"viewIncrease":597,"isOut":false,"isNew":false,"videoId":"a5KcO1hAczg","videoUrl":"https://youtube.com/watch?v=a5KcO1hAczg","previousRank":175,"rankChange":7,"changeType":"up","previousWeekViewIncrease":439},{"rank":169,"title":".mp3 feat. 花隈千冬","artist":"イナナキ","englishTitle":".mp3 feat. Hanakuma Chifuyu","englishArtist":"inanaki","views":648,"viewIncrease":594,"isOut":false,"isNew":false,"videoId":"BmyIruZrfVw","videoUrl":"https://youtube.com/watch?v=BmyIruZrfVw","previousRank":217,"rankChange":48,"changeType":"up","previousWeekViewIncrease":54},{"rank":170,"title":"ACCELATE!! feat. 初音ミク","artist":"Sumia","englishTitle":"ACCELATE!! feat. Hatsune Miku","englishArtist":"Sumia","views":12731,"viewIncrease":574,"isOut":false,"isNew":false,"videoId":"ovxZu7Vm6FI","videoUrl":"https://youtube.com/watch?v=ovxZu7Vm6FI","previousRank":170,"rankChange":0,"changeType":"same","previousWeekViewIncrease":520},{"rank":171,"title":"生存論 feat. 花隈千冬","artist":"metamol","englishTitle":"Seizonron feat. Hanakuma Chifuyu","englishArtist":"metamol","views":2677,"viewIncrease":501,"isOut":false,"isNew":false,"videoId":"q7RupHYSX3Y","videoUrl":"https://youtube.com/watch?v=q7RupHYSX3Y","previousRank":171,"rankChange":0,"changeType":"same","previousWeekViewIncrease":518},{"rank":172,"title":"Phenol feat. 可不","artist":"雨夜倫","englishTitle":"Phenol feat. KAFU","englishArtist":"雨夜倫","views":498,"viewIncrease":498,"isOut":false,"isNew":true,"videoId":"6luDDQL1kVw","videoUrl":"https://youtube.com/watch?v=6luDDQL1kVw","rankChange":null,"changeType":"new","previousWeekViewIncrease":0},{"rank":173,"title":"ダブルディスタン","artist":"Dios/シグナルP","englishTitle":"Double Distance","englishArtist":"Dios/SignalP","views":5650,"viewIncrease":498,"isOut":false,"isNew":false,"videoId":"Zmoidzg5SCA","videoUrl":"https://youtube.com/watch?v=Zmoidzg5SCA","previousRank":176,"rankChange":3,"changeType":"up","previousWeekViewIncrease":433},{"rank":174,"title":"兎角も謎 feat. 初音ミク","artist":"IDONO KAWAZU","englishTitle":"Tokaku mo Nazo feat. Hatsune Miku","englishArtist":"IDONO KAWAZU","views":22606,"viewIncrease":498,"isOut":false,"isNew":false,"videoId":"dTBpWXEzWHQ","videoUrl":"https://youtube.com/watch?v=dTBpWXEzWHQ","previousRank":169,"rankChange":-5,"changeType":"down","previousWeekViewIncrease":522},{"rank":175,"title":"Tokyo Nightmare? feat. 可不","artist":"21 Clown","englishTitle":"Tokyo Nightmare? feat. KAFU","englishArtist":"21 Clown","views":16045,"viewIncrease":472,"isOut":false,"isNew":false,"videoId":"WssRIlVOy6c","videoUrl":"https://youtube.com/watch?v=WssRIlVOy6c","previousRank":168,"rankChange":-7,"changeType":"down","previousWeekViewIncrease":522},{"rank":176,"title":"わかんないな feat.初音ミク","artist":"Celery","englishTitle":"Wakannai na feat. Hatsune Miku","englishArtist":"Celery","views":126850,"viewIncrease":471,"isOut":false,"isNew":false,"videoId":"9cKUhJ_N0Ro","videoUrl":"https://youtube.com/watch?v=9cKUhJ_N0Ro","previousRank":173,"rankChange":-3,"changeType":"down","previousWeekViewIncrease":468},{"rank":177,"title":"グリッチミュート feat. 初音ミク","artist":"雨ノ漣","englishTitle":"Glitch Mute feat. Hatsune Miku","englishArtist":"Ame no Sazanami","views":22682,"viewIncrease":457,"isOut":false,"isNew":false,"videoId":"H6AR5jpMRIQ","videoUrl":"https://youtube.com/watch?v=H6AR5jpMRIQ","previousRank":174,"rankChange":-3,"changeType":"down","previousWeekViewIncrease":460},{"rank":178,"title":"普通じゃない feat. 可不","artist":"前線","englishTitle":"Fuutsu Janai feat. KAFU","englishArtist":"zensen","views":12022,"viewIncrease":403,"isOut":false,"isNew":false,"videoId":"Tn-ThIoX6oI","videoUrl":"https://youtube.com/watch?v=Tn-ThIoX6oI","previousRank":183,"rankChange":5,"changeType":"up","previousWeekViewIncrease":335},{"rank":179,"title":"divEは笑わない / 初音ミク","artist":"淡雪こだま","englishTitle":"DivE wa Warawanai / Hatsune Miku","englishArtist":"Awayuki Kodama","views":1623,"viewIncrease":394,"isOut":false,"isNew":false,"videoId":"C1x_dANJ71I","videoUrl":"https://youtube.com/watch?v=C1x_dANJ71I","previousRank":142,"rankChange":-37,"changeType":"down","previousWeekViewIncrease":1229},{"rank":180,"title":"ハカイオーダー feat. 初音ミク","artist":"だら","englishTitle":"Hakai Order feat. Hatsune Miku","englishArtist":"DARA","views":392,"viewIncrease":392,"isOut":false,"isNew":true,"videoId":"PoeKpiGCXVs","videoUrl":"https://youtube.com/watch?v=PoeKpiGCXVs","rankChange":null,"changeType":"new","previousWeekViewIncrease":0},{"rank":181,"title":"信仰ですわ feat. グミ","artist":"犬飼","englishTitle":"Shinkou desu wa feat. GUMI","englishArtist":"Inukai","views":6739,"viewIncrease":389,"isOut":false,"isNew":false,"videoId":"vs4emaqWTyE","videoUrl":"https://youtube.com/watch?v=vs4emaqWTyE","previousRank":181,"rankChange":0,"changeType":"same","previousWeekViewIncrease":351},{"rank":182,"title":"晩夏祭 feat.初音ミク","artist":"Yuuyu","englishTitle":"Bankasai feat.Hatsune Miku","englishArtist":"Yuuyu","views":5196,"viewIncrease":384,"isOut":false,"isNew":false,"videoId":"9bkl9ky5N4o","videoUrl":"https://youtube.com/watch?v=9bkl9ky5N4o","previousRank":186,"rankChange":4,"changeType":"up","previousWeekViewIncrease":305},{"rank":183,"title":"いないいない feat. りむる","artist":"めろくる","englishTitle":"Inai Inai feat. Rimuru","englishArtist":"Mellowcle","views":6607,"viewIncrease":363,"isOut":false,"isNew":false,"videoId":"ZqiKhOz0Nq4","videoUrl":"https://youtube.com/watch?v=ZqiKhOz0Nq4","previousRank":184,"rankChange":1,"changeType":"up","previousWeekViewIncrease":315},{"rank":184,"title":"劣等感尋常じゃないわ feat. 初音ミク","artist":"Tategami","englishTitle":"Rettoukan Jinjou Janai wa","englishArtist":"Tategami","views":1935,"viewIncrease":355,"isOut":false,"isNew":false,"videoId":"7SLW8lXZQ5s","videoUrl":"https://youtube.com/watch?v=7SLW8lXZQ5s","previousRank":152,"rankChange":-32,"changeType":"down","previousWeekViewIncrease":901},{"rank":185,"title":"SLAUGHTXR feat. 初音ミク","artist":"北沢強兵","englishTitle":"SLAUGHTXR feat. Hatsune Miku","englishArtist":"Kitazawa Kyouhei","views":3882,"viewIncrease":345,"isOut":false,"isNew":false,"videoId":"tE7j8zXNMLQ","videoUrl":"https://youtube.com/watch?v=tE7j8zXNMLQ","previousRank":180,"rankChange":-5,"changeType":"down","previousWeekViewIncrease":379},{"rank":186,"title":"なぜなに？シンパシー feat. 可不","artist":"ナナホシ管弦楽団","englishTitle":"nazenani? sympathy feat. KAFU","englishArtist":"Nanahoshi Orchestra","views":14304,"viewIncrease":338,"isOut":false,"isNew":false,"videoId":"aLt2KAdjte4","videoUrl":"https://youtube.com/watch?v=aLt2KAdjte4","previousRank":179,"rankChange":-7,"changeType":"down","previousWeekViewIncrease":401},{"rank":187,"title":"ファーレン・ナイト feat. 初音ミク","artist":"nogi","englishTitle":"Fahren Night feat. Hatsune Miku","englishArtist":"nogi","views":2060,"viewIncrease":337,"isOut":false,"isNew":false,"videoId":"JhBjpCB6CpU","videoUrl":"https://youtube.com/watch?v=JhBjpCB6CpU","previousRank":163,"rankChange":-24,"changeType":"down","previousWeekViewIncrease":629},{"rank":188,"title":"マーマーレード・メイポール feat. flower","artist":"EN0N","englishTitle":"Marmalade ・ Maypole feat. flower","englishArtist":"EN0N","views":7771,"viewIncrease":310,"isOut":false,"isNew":false,"videoId":"IYJ48NnbGQ8","videoUrl":"https://youtube.com/watch?v=IYJ48NnbGQ8","previousRank":201,"rankChange":13,"changeType":"up","previousWeekViewIncrease":175},{"rank":189,"title":"青春死体 feat. 可不","artist":"Nem","englishTitle":"Seishun Shitai feat. KAFU","englishArtist":"Nem","views":2676,"viewIncrease":305,"isOut":false,"isNew":false,"videoId":"HLjU8pk6B3A","videoUrl":"https://youtube.com/watch?v=HLjU8pk6B3A","previousRank":192,"rankChange":3,"changeType":"up","previousWeekViewIncrease":224},{"rank":190,"title":"余命二年 feat. 初音ミク","artist":"はるな","englishTitle":"Yomei Ninen feat. Hatsune Miku","englishArtist":"haruna","views":8100,"viewIncrease":282,"isOut":false,"isNew":false,"videoId":"XGVMBG-0eBg","videoUrl":"https://youtube.com/watch?v=XGVMBG-0eBg","previousRank":191,"rankChange":1,"changeType":"up","previousWeekViewIncrease":226},{"rank":191,"title":"Another feat. ゲキヤク","artist":"NIL","englishTitle":"Another feat. Gekiyaku","englishArtist":"NIL","views":11455,"viewIncrease":274,"isOut":false,"isNew":false,"videoId":"FDc2uzDCBRo","videoUrl":"https://youtube.com/watch?v=FDc2uzDCBRo","previousRank":190,"rankChange":-1,"changeType":"down","previousWeekViewIncrease":232},{"rank":192,"title":"狂騒列車 feat. ついなちゃん","artist":"キツネリ","englishTitle":"Kyousou Ressha feat. Tsuina-chan","englishArtist":"Kitsuneri","views":6144,"viewIncrease":272,"isOut":false,"isNew":false,"videoId":"AOw7f4F8So4","videoUrl":"https://youtube.com/watch?v=AOw7f4F8So4","previousRank":189,"rankChange":-3,"changeType":"down","previousWeekViewIncrease":240},{"rank":193,"title":"tonight feat. 初音ミク","artist":"配慮","englishTitle":"tonight feat. Hatsune Miku","englishArtist":"Hairy","views":3721,"viewIncrease":258,"isOut":false,"isNew":false,"videoId":"oXdWGVb0MPs","videoUrl":"https://youtube.com/watch?v=oXdWGVb0MPs","previousRank":188,"rankChange":-5,"changeType":"down","previousWeekViewIncrease":253},{"rank":194,"title":"見得 feat. 初音ミク, 鏡音リン, 可不","artist":"IDONO KAWAZU","englishTitle":"Mie feat. Hatsune Miku, Kagamine Rin, KAFU","englishArtist":"IDONO KAWAZU","views":10699,"viewIncrease":255,"isOut":false,"isNew":false,"videoId":"96Ep3k-29TU","videoUrl":"https://youtube.com/watch?v=96Ep3k-29TU","previousRank":187,"rankChange":-7,"changeType":"down","previousWeekViewIncrease":276},{"rank":195,"title":"film feat. ナースロボ＿タイプＴ, 初音ミク","artist":"HotαRu","englishTitle":"film feat. Nurse Robot_Type T, Hatsune Miku","englishArtist":"HotαRu","views":237,"viewIncrease":237,"isOut":false,"isNew":true,"videoId":"wjXw4sLF-qY","videoUrl":"https://youtube.com/watch?v=wjXw4sLF-qY","rankChange":null,"changeType":"new","previousWeekViewIncrease":0},{"rank":196,"title":"アルコ・ホリック・シンデレラ feat. 初音ミク","artist":"ヤマギシコージ","englishTitle":"Alcoholic Cinderella feat. Hatsune Miku","englishArtist":"Yamagi Shikouji","views":3581,"viewIncrease":237,"isOut":false,"isNew":false,"videoId":"bKB-XBtVGdA","videoUrl":"https://youtube.com/watch?v=bKB-XBtVGdA","previousRank":194,"rankChange":-2,"changeType":"down","previousWeekViewIncrease":215},{"rank":197,"title":"逃奔 feat. 可不","artist":"いめ44","englishTitle":"tou-hon feat. KAFU","englishArtist":"ime44","views":2237,"viewIncrease":224,"isOut":false,"isNew":false,"videoId":"g8tvOOMajOU","videoUrl":"https://youtube.com/watch?v=g8tvOOMajOU","previousRank":177,"rankChange":-20,"changeType":"down","previousWeekViewIncrease":431},{"rank":198,"title":"Crystal Memory feat. IA","artist":"Roca","englishTitle":"Crystal Memory feat. IA","englishArtist":"Roca","views":2629,"viewIncrease":211,"isOut":false,"isNew":false,"videoId":"PrOHuaiZPe4","videoUrl":"https://youtube.com/watch?v=PrOHuaiZPe4","previousRank":196,"rankChange":-2,"changeType":"down","previousWeekViewIncrease":200},{"rank":199,"title":"マニアカル feat. 可不","artist":"よたばいと","englishTitle":"Maniacal feat. KAFU","englishArtist":"Yotta Byte","views":2649,"viewIncrease":198,"isOut":false,"isNew":false,"videoId":"Zr8isHTRIUI","videoUrl":"https://youtube.com/watch?v=Zr8isHTRIUI","previousRank":193,"rankChange":-6,"changeType":"down","previousWeekViewIncrease":223},{"rank":200,"title":"Raspberry Mode feat. 重音テト","artist":"Capchii","englishTitle":"Raspberry Mode feat. Kasane Teto","englishArtist":"Capchii","views":5639,"viewIncrease":195,"isOut":false,"isNew":false,"videoId":"pzrvCB2jPFo","videoUrl":"https://youtube.com/watch?v=pzrvCB2jPFo","previousRank":198,"rankChange":-2,"changeType":"down","previousWeekViewIncrease":193},{"rank":201,"title":"Turning Point. feat. Mai","artist":"雪乃イト","englishTitle":"Turning Point. feat. Mai","englishArtist":"Yukino Ito","views":6211,"viewIncrease":193,"isOut":false,"isNew":false,"videoId":"Tt_FxclW6FE","videoUrl":"https://youtube.com/watch?v=Tt_FxclW6FE","previousRank":206,"rankChange":5,"changeType":"up","previousWeekViewIncrease":123},{"rank":202,"title":"アフェクタ feat. 鏡音リン","artist":"Tonbi","englishTitle":"Affector feat. Kagamine Rin","englishArtist":"Tonbi","views":5913,"viewIncrease":187,"isOut":false,"isNew":false,"videoId":"krCUasaG4Ac","videoUrl":"https://youtube.com/watch?v=krCUasaG4Ac","previousRank":207,"rankChange":5,"changeType":"up","previousWeekViewIncrease":116},{"rank":203,"title":"グッド・バイ feat. 可不","artist":"宮之悟","englishTitle":"Good Bye feat. KAFU","englishArtist":"Miyano Satoru","views":8726,"viewIncrease":186,"isOut":false,"isNew":false,"videoId":"kB-aMUHqOd4","videoUrl":"https://youtube.com/watch?v=kB-aMUHqOd4","previousRank":153,"rankChange":-50,"changeType":"down","previousWeekViewIncrease":881},{"rank":204,"title":"合法メンヘラ暴走ドラッグ feat. AiSuu","artist":"もかねこ","englishTitle":"Gouhou Menhera Bousou Drug feat. AiSuu","englishArtist":"Mokaneko","views":10535,"viewIncrease":181,"isOut":false,"isNew":false,"videoId":"cIwBPDsZ9z8","videoUrl":"https://youtube.com/watch?v=cIwBPDsZ9z8","previousRank":167,"rankChange":-37,"changeType":"down","previousWeekViewIncrease":527},{"rank":205,"title":"ピラニア feat. MYK-IV","artist":"アイラ","englishTitle":"Piranha feat. MYK-IV","englishArtist":"Aira","views":5042,"viewIncrease":176,"isOut":false,"isNew":false,"videoId":"b7XkBjGKWW0","videoUrl":"https://youtube.com/watch?v=b7XkBjGKWW0","previousRank":197,"rankChange":-8,"changeType":"down","previousWeekViewIncrease":199},{"rank":206,"title":"7days feat. 初音ミク","artist":"雨飴","englishTitle":"7days feat. Hatsune Miku","englishArtist":"Ameame","views":4454,"viewIncrease":154,"isOut":false,"isNew":false,"videoId":"qYC_sqVSJvE","videoUrl":"https://youtube.com/watch?v=qYC_sqVSJvE","previousRank":202,"rankChange":-4,"changeType":"down","previousWeekViewIncrease":168},{"rank":207,"title":"タンジブルドロップ feat. 初音ミク","artist":"たぴぼ！！","englishTitle":"Tangible Drop feat. Hatsune Miku","englishArtist":"tapibo!!","views":2691,"viewIncrease":143,"isOut":false,"isNew":false,"videoId":"lvTJe4VvSyc","videoUrl":"https://youtube.com/watch?v=lvTJe4VvSyc","previousRank":204,"rankChange":-3,"changeType":"down","previousWeekViewIncrease":147},{"rank":208,"title":"夏の日 feat. 可不","artist":"西憂花","englishTitle":"Natsu no Hi feat. KAFU","englishArtist":"Nishi Yuuka","views":2164,"viewIncrease":141,"isOut":false,"isNew":false,"videoId":"qCQ_xdEN4ZI","videoUrl":"https://youtube.com/watch?v=qCQ_xdEN4ZI","previousRank":211,"rankChange":3,"changeType":"up","previousWeekViewIncrease":94},{"rank":209,"title":"ビースティ feat. 初音ミク","artist":"サカダケイ","englishTitle":"Beastie feat. Hatsune Miku","englishArtist":"Sakadakei","views":2429,"viewIncrease":124,"isOut":false,"isNew":false,"videoId":"HJ0X8xnbVVk","videoUrl":"https://youtube.com/watch?v=HJ0X8xnbVVk","previousRank":209,"rankChange":0,"changeType":"same","previousWeekViewIncrease":103},{"rank":210,"title":"狼と鴉、獣の唄 feat. Mai","artist":"パル","englishTitle":"Ookami to Karasu, Kedamono no Uta feat. Mai","englishArtist":"Paru","views":20782,"viewIncrease":114,"isOut":false,"isNew":false,"videoId":"x8kLFSV0RV8","videoUrl":"https://youtube.com/watch?v=x8kLFSV0RV8","previousRank":200,"rankChange":-10,"changeType":"down","previousWeekViewIncrease":177},{"rank":211,"title":"時間旅行 feat. 初音ミク","artist":"りゅーりゅー","englishTitle":"Jikan Ryokou feat. Hatsune Miku","englishArtist":"ryuryu","views":4441,"viewIncrease":108,"isOut":false,"isNew":false,"videoId":"KKS7JLs9UfU","videoUrl":"https://youtube.com/watch?v=KKS7JLs9UfU","previousRank":205,"rankChange":-6,"changeType":"down","previousWeekViewIncrease":126},{"rank":212,"title":"躁鬱 feat. 初音ミク","artist":"KiЯa","englishTitle":"Souutsu feat. Hatsune Miku","englishArtist":"KiЯa","views":2759,"viewIncrease":107,"isOut":false,"isNew":false,"videoId":"6nNIjDHG4lY","videoUrl":"https://youtube.com/watch?v=6nNIjDHG4lY","previousRank":210,"rankChange":-2,"changeType":"down","previousWeekViewIncrease":101},{"rank":213,"title":"3.4feet feat. カゼヒキ, flower","artist":"君嶋スイ","englishTitle":"3.4feet feat. Kazehiki, flower","englishArtist":"Kimizima Sui","views":3581,"viewIncrease":100,"isOut":false,"isNew":false,"videoId":"8k1lEpQcLSA","videoUrl":"https://youtube.com/watch?v=8k1lEpQcLSA","previousRank":203,"rankChange":-10,"changeType":"down","previousWeekViewIncrease":168},{"rank":214,"title":"ミスタージョーカー feat. イア","artist":"しゃいと","englishTitle":"Mr. Joker feat. IA","englishArtist":"shaito","views":2775,"viewIncrease":98,"isOut":false,"isNew":false,"videoId":"DY0vywzyNPo","videoUrl":"https://youtube.com/watch?v=DY0vywzyNPo","previousRank":212,"rankChange":-2,"changeType":"down","previousWeekViewIncrease":83},{"rank":215,"title":"ユーエンミィ feat. 狐子, flower","artist":"マドロミ","englishTitle":"You & Me feat. COKO, flower","englishArtist":"Madoromi","views":1070,"viewIncrease":88,"isOut":false,"isNew":false,"videoId":"ZeHbQgP71Kg","videoUrl":"https://youtube.com/watch?v=ZeHbQgP71Kg","previousRank":216,"rankChange":1,"changeType":"up","previousWeekViewIncrease":55},{"rank":216,"title":"あなたのいない夏 feat. 音街ウナ","artist":"ひらぎ","englishTitle":"Anata no Inai Natsu feat. Otomachi Una","englishArtist":"Hiragi","views":1084,"viewIncrease":85,"isOut":false,"isNew":false,"videoId":"wGIhAxmwLhw","videoUrl":"https://youtube.com/watch?v=wGIhAxmwLhw","previousRank":208,"rankChange":-8,"changeType":"down","previousWeekViewIncrease":106},{"rank":217,"title":"背景病 feat. 歌愛ユキ","artist":"ななし","englishTitle":"Haikeibyou feat. Kaai Yuki","englishArtist":"Nanashi","views":2740,"viewIncrease":83,"isOut":false,"isNew":false,"videoId":"Fz7rgXBCZ8w","videoUrl":"https://youtube.com/watch?v=Fz7rgXBCZ8w","previousRank":213,"rankChange":-4,"changeType":"down","previousWeekViewIncrease":78},{"rank":218,"title":"命の願い feat. 初音ミク","artist":"Kuratu","englishTitle":"Inochi no Negai feat. Hatsune Miku","englishArtist":"Kuratu","views":2893,"viewIncrease":67,"isOut":false,"isNew":false,"videoId":"3Eyo7SSdGjU","videoUrl":"https://youtube.com/watch?v=3Eyo7SSdGjU","previousRank":218,"rankChange":0,"changeType":"same","previousWeekViewIncrease":51},{"rank":219,"title":"Chu feat. 可不","artist":"tekalu","englishTitle":"Chu feat. KAFU","englishArtist":"tekalu","views":2767,"viewIncrease":65,"isOut":false,"isNew":false,"videoId":"90xkKQ9WKPw","videoUrl":"https://youtube.com/watch?v=90xkKQ9WKPw","previousRank":224,"rankChange":5,"changeType":"up","previousWeekViewIncrease":36},{"rank":220,"title":"Down Down Down feat. 可不","artist":"てづ","englishTitle":"Down Down Down feat. KAFU","englishArtist":"Tezu","views":1231,"viewIncrease":53,"isOut":false,"isNew":false,"videoId":"Uqs26fNAMbY","videoUrl":"https://youtube.com/watch?v=Uqs26fNAMbY","previousRank":219,"rankChange":-1,"changeType":"down","previousWeekViewIncrease":46},{"rank":221,"title":"bubble wrap feat. 初音ミク","artist":"ライクア","englishTitle":"bubble wrap feat. Hatsune Miku","englishArtist":"LikeA","views":1363,"viewIncrease":50,"isOut":false,"isNew":false,"videoId":"qpyt5ku-tWA","videoUrl":"https://youtube.com/watch?v=qpyt5ku-tWA","previousRank":222,"rankChange":1,"changeType":"up","previousWeekViewIncrease":41},{"rank":222,"title":"ニューレトロ feat. 鏡音リン","artist":"つかりょ","englishTitle":"New Retro feat. Kagamine Rin","englishArtist":"Tsukaryo","views":2532,"viewIncrease":50,"isOut":false,"isNew":false,"videoId":"F7WbO1mZfpI","videoUrl":"https://youtube.com/watch?v=F7WbO1mZfpI","previousRank":226,"rankChange":4,"changeType":"up","previousWeekViewIncrease":34},{"rank":223,"title":"ハンパな徳じゃ罪になる feat. 初音ミク","artist":"マロン菩薩","englishTitle":"Insane Virtue feat. Hatsune Miku","englishArtist":"Marron Bosatsu","views":2052,"viewIncrease":47,"isOut":false,"isNew":false,"videoId":"HrnuKbPWSYw","videoUrl":"https://youtube.com/watch?v=HrnuKbPWSYw","previousRank":220,"rankChange":-3,"changeType":"down","previousWeekViewIncrease":46},{"rank":224,"title":"オクシモロン feat. Mai","artist":"ていぬ","englishTitle":"Oxymoron feat. Mai","englishArtist":"Teinu","views":915,"viewIncrease":42,"isOut":false,"isNew":false,"videoId":"VPbsefV0OtA","videoUrl":"https://youtube.com/watch?v=VPbsefV0OtA","previousRank":234,"rankChange":10,"changeType":"up","previousWeekViewIncrease":23},{"rank":225,"title":"Until now feat. 初音ミク","artist":"Qvi","englishTitle":"Until now feat. Hatsune Miku","englishArtist":"Qvi","views":865,"viewIncrease":41,"isOut":false,"isNew":false,"videoId":"W27rmOIFRWs","videoUrl":"https://youtube.com/watch?v=W27rmOIFRWs","previousRank":227,"rankChange":2,"changeType":"up","previousWeekViewIncrease":33},{"rank":226,"title":"ばなそに叱られる！ｗｗｗ feat. 初音ミク","artist":"Shu","englishTitle":"Banaso ni Shikarareru! Www","englishArtist":"Shu","views":1500,"viewIncrease":37,"isOut":false,"isNew":false,"videoId":"Vh7XuBTDSjg","videoUrl":"https://youtube.com/watch?v=Vh7XuBTDSjg","previousRank":223,"rankChange":-3,"changeType":"down","previousWeekViewIncrease":40},{"rank":227,"title":"ドクゼリ feat. 歌愛ユキ, 初音ミク","artist":"ZIIEK","englishTitle":"Cicuta Virosa feat. Kaai Yuki, Hatsune Miku","englishArtist":"ZIIEK","views":1007,"viewIncrease":36,"isOut":false,"isNew":false,"videoId":"7Y_bWO-iOtM","videoUrl":"https://youtube.com/watch?v=7Y_bWO-iOtM","previousRank":231,"rankChange":4,"changeType":"up","previousWeekViewIncrease":27},{"rank":228,"title":"for gone feat. 可不","artist":"Matsu＊","englishTitle":"for gone feat. KAFU","englishArtist":"Matsu＊","views":275,"viewIncrease":34,"isOut":false,"isNew":false,"videoId":"oX75lkLf5WI","videoUrl":"https://youtube.com/watch?v=oX75lkLf5WI","previousRank":236,"rankChange":8,"changeType":"up","previousWeekViewIncrease":22},{"rank":229,"title":"SOGGY feat. 可不","artist":"GLI","englishTitle":"SOGGY feat. KAFU","englishArtist":"GLI","views":661,"viewIncrease":29,"isOut":false,"isNew":false,"videoId":"9g-wnOBCe6U","videoUrl":"https://youtube.com/watch?v=9g-wnOBCe6U","previousRank":221,"rankChange":-8,"changeType":"down","previousWeekViewIncrease":45},{"rank":230,"title":"誰かと似ている彼氏 feat. 初音ミク","artist":"R Sound Design","englishTitle":"My Lookalike Boyfriend","englishArtist":"R Sound Design","views":2520,"viewIncrease":21,"isOut":false,"isNew":false,"videoId":"EUu1zbNTjp8","videoUrl":"https://youtube.com/watch?v=EUu1zbNTjp8","previousRank":233,"rankChange":3,"changeType":"up","previousWeekViewIncrease":24},{"rank":231,"title":"ストラグルベイビー feat. 初音ミク","artist":"乙幡","englishTitle":"Struggle Baby feat. Hatsune Miku","englishArtist":"Otsubata","views":889,"viewIncrease":20,"isOut":false,"isNew":false,"videoId":"5zyBoyNHJlk","videoUrl":"https://youtube.com/watch?v=5zyBoyNHJlk","previousRank":230,"rankChange":-1,"changeType":"down","previousWeekViewIncrease":27},{"rank":232,"title":"水商売 feat. Flower","artist":"莉津","englishTitle":"Mizushoubai feat. Flower","englishArtist":"Ritsu","views":2128,"viewIncrease":19,"isOut":false,"isNew":false,"videoId":"K9OZwX04D0s","videoUrl":"https://youtube.com/watch?v=K9OZwX04D0s","previousRank":229,"rankChange":-3,"changeType":"down","previousWeekViewIncrease":28},{"rank":233,"title":"逆光ファンタジア feat. v4 フラワ","artist":"Yo-SK","englishTitle":"Gyakkou Fantasia feat. v4 flower","englishArtist":"Yo-SK","views":1296,"viewIncrease":14,"isOut":false,"isNew":false,"videoId":"uEY2DjponhA","videoUrl":"https://youtube.com/watch?v=uEY2DjponhA","previousRank":240,"rankChange":7,"changeType":"up","previousWeekViewIncrease":17},{"rank":234,"title":"ネットサーフィン feat. 初音ミク","artist":"ぷぅちる","englishTitle":"Internet surfing feat. Hatsune Miku","englishArtist":"Puchiru","views":315,"viewIncrease":12,"isOut":false,"isNew":false,"videoId":"xbIsfwavocA","videoUrl":"https://youtube.com/watch?v=xbIsfwavocA","previousRank":237,"rankChange":3,"changeType":"up","previousWeekViewIncrease":21},{"rank":235,"title":"フルムーン＝ナイトフィーバー feat. 音街ウナ","artist":"やなこ","englishTitle":"Full Moon=Night Fever feat. Otomachi Una","englishArtist":"Yanako","views":284,"viewIncrease":11,"isOut":false,"isNew":false,"videoId":"j5-s9eA8KtE","videoUrl":"https://youtube.com/watch?v=j5-s9eA8KtE","previousRank":238,"rankChange":3,"changeType":"up","previousWeekViewIncrease":19},{"rank":236,"title":"踊れ藍路に feat. 初音ミク","artist":"つーくん","englishTitle":"Odore Airo ni feat. Hatsune Miku","englishArtist":"Tsu-kun","views":127,"viewIncrease":1,"isOut":false,"isNew":false,"videoId":"YnWsFvfruAI","videoUrl":"https://youtube.com/watch?v=YnWsFvfruAI","previousRank":243,"rankChange":7,"changeType":"up","previousWeekViewIncrease":3},{"rank":237,"title":"みんなで歌おう！ feat. 洛天依","artist":"おばけP","englishTitle":"Minna de Utaou! feat. Luo Tianyi","englishArtist":"OBAKE_P","views":328,"viewIncrease":-1,"isOut":false,"isNew":false,"videoId":"CuObqN6N4Sg","videoUrl":"https://youtube.com/watch?v=CuObqN6N4Sg","previousRank":242,"rankChange":5,"changeType":"up","previousWeekViewIncrease":8}],"hasRankChanges":true}