{"additionalNames":"HATSUNE MIKU EXPO 2026 London","category":"Unspecified","date":"2026-11-12T00:00:00Z","description":"Illustration by [鈴ノ助](https://vocadb.net/Ar/2123)","id":12222,"mainPicture":{"mime":"image/jpeg","urlOriginal":"https://static.vocadb.net/img/ReleaseEvent/mainOrig/12222.jpg?v=7","urlSmallThumb":"https://static.vocadb.net/img/ReleaseEvent/mainSmall/12222.jpg?v=7","urlThumb":"https://static.vocadb.net/img/ReleaseEvent/mainThumb/12222.jpg?v=7","urlTinyThumb":"https://static.vocadb.net/img/ReleaseEvent/mainTiny/12222.jpg?v=7"},"name":"MIKU EXPO 2026 London","names":[{"language":"English","value":"MIKU EXPO 2026 London"},{"language":"Unspecified","value":"HATSUNE MIKU EXPO 2026 London"}],"series":{"additionalNames":"HATSUNE MIKU EXPO","category":"Concert","deleted":false,"description":"Miku Expo refers to a series of concert performances and venues featuring the Piapro characters (Hatsune Miku, Kagamine Rin, Kagamine Len, Megurine Luka, MEIKO and KAITO). There have been events in the United States, Mexico, China, Indonesia, Malaysia, and more.\r\n2014 - present.","id":82,"name":"MIKU EXPO","pictureMime":"image/jpeg","status":"Approved","urlSlug":"miku-expo","version":6},"seriesId":82,"seriesNumber":2026,"seriesSuffix":"London","status":"Finished","urlSlug":"miku-expo-2026-london","venueName":"The O2","version":7,"webLinks":[{"category":"Official","description":"X (Twitter)","disabled":false,"id":13614,"url":"https://x.com/mikuexpo/status/2024773462766805495"},{"category":"Other","description":"Website","disabled":false,"id":13615,"url":"https://mikuexpo.com/europe2026/"}]}