{"additionalNames":"","artists":[{"artist":{"additionalNames":"勝史, Masafumi","artistType":"Producer","deleted":false,"id":20,"name":"Clean Tears","pictureMime":"image/jpeg","status":"Approved","version":38},"categories":"Producer","effectiveRoles":"Default","id":6134,"isCustomName":false,"isSupport":false,"name":"Clean Tears","roles":"Default"},{"artist":{"additionalNames":"初音ミク, 初音未来, Chūyīn Wèilái, 하츠네 미쿠, 初音未來","artistType":"Vocaloid","deleted":false,"id":1,"name":"Hatsune Miku","pictureMime":"image/png","releaseDate":"2007-08-31T00:00:00Z","status":"Locked","version":39},"categories":"Vocalist","effectiveRoles":"Default","id":6135,"isCustomName":false,"isSupport":false,"name":"Hatsune Miku","roles":"Default"},{"artist":{"additionalNames":"","artistType":"Lyricist","deleted":false,"id":1436,"name":"T-ism","pictureMime":"image/jpeg","status":"Finished","version":7},"categories":"Other","effectiveRoles":"Lyricist","id":76925,"isCustomName":false,"isSupport":false,"name":"T-ism","roles":"Default"}],"artistString":"Clean Tears feat. Hatsune Miku","createDate":"2011-12-11T20:32:31","defaultName":"Love it!","defaultNameLanguage":"English","favoritedTimes":4,"id":5106,"lengthSeconds":329,"mainPicture":{"urlOriginal":"https://i1.ytimg.com/vi/h69cxXdHHO0/hqdefault.jpg","urlThumb":"https://i.ytimg.com/vi/h69cxXdHHO0/default.jpg"},"maxMilliBpm":127000,"minMilliBpm":127000,"name":"Love it!","names":[{"language":"English","value":"Love it!"}],"publishDate":"2008-12-29T00:00:00Z","pvs":[{"author":"Linoleumallkay2","description":"Track 1 From the vocaloid album titled Love it! made back in 2008 album and producer is by clean tears S.C.X","disabled":false,"id":1257358,"length":329,"name":"「LOVE IT!」Hatsune Miku - Love it! (HD)","publishDate":"2025-07-27T00:00:00","pvId":"h69cxXdHHO0","service":"Youtube","pvType":"Other","thumbUrl":"https://i.ytimg.com/vi/h69cxXdHHO0/default.jpg","url":"https://youtu.be/h69cxXdHHO0"},{"author":"lurnasp","description":"初めて君を見たときから一目惚れしてたよ\r\n運命だなんて言葉じゃ軽すぎて\r\n\r\n今すぐ君の所へ迎えに行くからね\r\n高鳴る胸の鼓動は君に届くかな\r\n\r\n始まるよ僕たちの新しい形 愛情の欠片たち二つ合わせて\r\n君がいるそれだけで笑顔になれるよ不思議な魔法だね\r\nまんまるの君の目が僕を映すとき君の目はいつだって笑ってるんだ\r\n君がいるそれだけで全てが変わるような魔法に満ちてくよ\r\n\r\n君はマジカルキューピット Love itの魔法だね\r\n恋のマジカルキューピット Love itの魔法ね\r\n\r\nピンと伸ばしきったお耳は何を探してるの\r\n不安そうに怯える君に微笑んだ\r\n\r\n今すぐ君に何か名前を付けてあげよう\r\n誰にも負けないくらいかわいい名前を\r\n\r\n始まるよ僕たちの新しい暮らし この部屋を喜びが全部包んで\r\n君が居るそれだけで笑顔になれるよ不思議な魔法だね\r\n聞こえるよ新しい風の抜ける音 爽やかに軽やかに駆け抜けていく\r\n君が居るそれだけで全てが変わるような魔法が溢れてる\r\n\r\n君はマジカルキューピット Love itの魔法だね\r\n恋のマジカルキューピット Love itをどうぞ\r\n\r\n君の全てを愛しているからね\r\nいつまでもこうして微笑んでいるよいつでも\r\n時が過ぎても\r\n\r\n変わらない関係と無償の絆をいくらでも君に教えてあげるから\r\n変わらない微笑をまた今日もあげよう魔法に変わるかな\r\n呼んでるよ君のこといくらでも愛を言の葉の端に乗せ君にあげるよ\r\n君を呼ぶそれだけで全てが変わるような魔法に満ちてくよ\r\n\r\nLoveyはマジカルキューピット Love itの魔法だね\r\nLoveyはマジカルキューピット Love itさぁ笑顔でね\r\n\r\n初めて君を見たときから一目惚れしてたよ\r\n運命だなんて言葉じゃ軽すぎた","disabled":false,"id":1257359,"length":331,"name":"初音ミク Love it! Full Ver.","publishDate":"2009-08-18T00:00:00","pvId":"Wxnx3HMN7wc","service":"Youtube","pvType":"Other","thumbUrl":"https://i.ytimg.com/vi/Wxnx3HMN7wc/default.jpg","url":"https://youtu.be/Wxnx3HMN7wc"}],"pvServices":"Youtube","ratingScore":34,"songType":"Original","status":"Finished","thumbUrl":"https://i.ytimg.com/vi/h69cxXdHHO0/default.jpg","version":15,"webLinks":[{"category":"Reference","description":"MikuWiki","disabled":false,"id":112111,"url":"https://w.atwiki.jp/hmiku/pages/31019.html"},{"category":"Reference","description":"Vocaloid Wiki","disabled":false,"id":112112,"url":"https://vocaloid.fandom.com/wiki/Love_it!"}],"cultureCodes":["ja"]}