{"additionalNames":"メズマライザー, Mesmeriser, 메스머라이저, Mesmerizador, ผู้​ส​ะ​ก​ด​จิ​ต, فاتن","artists":[{"artist":{"additionalNames":"サツキ, Satsuki, 32ki_, 사츠키","artistType":"Producer","deleted":false,"id":75469,"name":"32ki","pictureMime":"image/png","status":"Finished","version":30},"categories":"Producer","effectiveRoles":"Arranger, Composer, Lyricist","id":1707091,"isCustomName":false,"isSupport":false,"name":"32ki","roles":"Arranger, Composer, Lyricist"},{"artist":{"additionalNames":"CASTSTATION, きゃすと, CAST, ちゃんねる, channelcaststation","artistType":"Animator","deleted":false,"id":124916,"name":"channel","pictureMime":"image/jpeg","status":"Approved","version":14},"categories":"Animator","effectiveRoles":"Animator","id":1728817,"isCustomName":false,"isSupport":false,"name":"channel","roles":"Animator"},{"artist":{"additionalNames":"ヒロモトヒライシン","artistType":"Producer","deleted":false,"id":89842,"name":"Hiromoto Hiraishin","pictureMime":"image/jpeg","status":"Finished","version":9},"categories":"Other","effectiveRoles":"Instrumentalist","id":1730010,"isCustomName":false,"isSupport":false,"name":"Hiromoto Hiraishin","roles":"Instrumentalist"},{"artist":{"additionalNames":"初音ミク V4X (Original), 初音ミク V4Xβ, Hatsune Miku V4Xβ","artistType":"Vocaloid","deleted":false,"id":50234,"name":"Hatsune Miku V4X (Original)","pictureMime":"image/png","releaseDate":"2016-08-31T00:00:00Z","status":"Finished","version":12},"categories":"Vocalist","effectiveRoles":"Default","id":1879418,"isCustomName":false,"isSupport":false,"name":"Hatsune Miku V4X (Original)","roles":"Default"},{"artist":{"additionalNames":"重音テトSV, Synthesizer V AI 重音テト, Synthesizer V AI Kasane Teto, 카사네 테토 SV","artistType":"SynthesizerV","deleted":false,"id":118397,"name":"Kasane Teto SV","pictureMime":"image/png","releaseDate":"2023-04-27T00:00:00Z","status":"Approved","version":23},"categories":"Vocalist","effectiveRoles":"Default","id":1879419,"isCustomName":false,"isSupport":false,"name":"Kasane Teto SV","roles":"Default"}],"artistString":"32ki feat. Hatsune Miku V4X (Original), Kasane Teto SV","createDate":"2024-04-08T18:31:03.637","defaultName":"メズマライザー","defaultNameLanguage":"Japanese","favoritedTimes":225,"id":610187,"lengthSeconds":157,"mainPicture":{"urlOriginal":"https://i1.ytimg.com/vi/19y8YTbvri8/hqdefault.jpg","urlThumb":"https://i.ytimg.com/vi/19y8YTbvri8/default.jpg"},"maxMilliBpm":185000,"minMilliBpm":185000,"name":"Mesmerizer","names":[{"language":"Japanese","value":"メズマライザー"},{"language":"English","value":"Mesmerizer"},{"language":"Unspecified","value":"Mesmeriser"},{"language":"Unspecified","value":"메스머라이저"},{"language":"Unspecified","value":"Mesmerizador"},{"language":"Unspecified","value":"ผู้​ส​ะ​ก​ด​จิ​ต"},{"language":"Unspecified","value":"فاتن"}],"publishDate":"2024-04-27T00:00:00Z","pvs":[{"author":"サツキ","disabled":false,"id":940508,"length":157,"name":"メズマライザー / 初音ミク・重音テトSV","publishDate":"2024-04-27T00:00:00","pvId":"19y8YTbvri8","service":"Youtube","pvType":"Original","thumbUrl":"https://i.ytimg.com/vi/19y8YTbvri8/default.jpg","url":"https://youtu.be/19y8YTbvri8"},{"author":"サツキ","disabled":false,"id":940509,"length":156,"name":"メズマライザー / 初音ミク・重音テトSV","publishDate":"2024-04-27T00:00:00","pvId":"sm43708803","service":"NicoNicoDouga","pvType":"Original","thumbUrl":"https://nicovideo.cdn.nimg.jp/thumbnails/43708803/43708803.68284955","url":"http://www.nicovideo.jp/watch/sm43708803"},{"author":"Satsukiサツキ","disabled":false,"extendedMetadata":{"json":"{\"Aid\":1254639592,\"Bvid\":\"BV15J4m1A7qy\",\"Cid\":1543404614}"},"id":953286,"length":158,"name":"【官方投稿】メズマライザー / 初音ミク・重音テトSV","publishDate":"2024-05-13T00:00:00","pvId":"1254639592","service":"Bilibili","pvType":"Original","thumbUrl":"http://i0.hdslb.com/bfs/archive/c4496e1c95132a8dd859f9ad52d92a7e58efec75.jpg","url":"https://www.bilibili.com/video/av1254639592"},{"author":"Satsuki - Topic","disabled":false,"id":954128,"length":157,"name":"メズマライザー (feat. 初音ミク & 重音テト)","publishDate":"2024-05-16T00:00:00","pvId":"ibjWftkJrd4","service":"Youtube","pvType":"Original","thumbUrl":"https://i.ytimg.com/vi/ibjWftkJrd4/default.jpg","url":"https://youtu.be/ibjWftkJrd4"},{"author":"サツキ","disabled":true,"id":1009415,"length":157,"name":"メズマライザー / 初音ミク・重音テトSV - Mesmerizer feat.Hatsune Miku & Kasane Teto","publishDate":"2024-08-17T00:00:00","pvId":"1899037407 32ki_may/mesmerizer","service":"SoundCloud","pvType":"Original","thumbUrl":"https://i1.sndcdn.com/artworks-gJfmS7kravcu3yGg-cOrLMg-original.jpg","url":"http://soundcloud.com/32ki_may/mesmerizer"},{"author":"Satsuki - Topic","disabled":false,"id":1019798,"length":157,"name":"メズマライザー (feat. 初音ミク & 重音テト)","publishDate":"2024-08-29T00:00:00","pvId":"sVCcqC3M1H4","service":"Youtube","pvType":"Original","thumbUrl":"https://i.ytimg.com/vi/sVCcqC3M1H4/default.jpg","url":"https://youtu.be/sVCcqC3M1H4"}],"pvServices":"NicoNicoDouga, Youtube, Bilibili","ratingScore":1283,"songType":"Original","status":"Approved","thumbUrl":"https://i.ytimg.com/vi/19y8YTbvri8/default.jpg","version":77,"webLinks":[{"category":"Official","description":"Miku and Teto character sheet","disabled":true,"id":146133,"url":"https://twitter.com/_CASTSTATION/status/1784162042066371062"},{"category":"Reference","description":"Vocaloid Lyrics Wiki","disabled":false,"id":146137,"url":"https://vocaloidlyrics.miraheze.org/wiki/%E3%83%A1%E3%82%BA%E3%83%9E%E3%83%A9%E3%82%A4%E3%82%B6%E3%83%BC_(Mesmerizer)"},{"category":"Reference","description":"Vocaloid Wiki","disabled":false,"id":146144,"url":"https://vocaloid.fandom.com/wiki/%E3%83%A1%E3%82%BA%E3%83%9E%E3%83%A9%E3%82%A4%E3%82%B6%E3%83%BC_(Mesmerizer)"},{"category":"Reference","description":"MikuWiki","disabled":false,"id":146205,"url":"https://w.atwiki.jp/hmiku/pages/60620.html"},{"category":"Official","description":"Pixiv Fanbox - thoughts on Mesmerizer's popularity","disabled":false,"id":146625,"url":"https://may-32ki.fanbox.cc/posts/7881903"},{"category":"Official","description":"\"WATCH THIS\" (Illustration)","disabled":true,"id":146949,"url":"https://twitter.com/_CASTSTATION/status/1787051327492948277"},{"category":"Official","description":"\"Attention!\" (Illustration)","disabled":true,"id":146950,"url":"https://twitter.com/_CASTSTATION/status/1789143397292560480"},{"category":"Official","description":"Twitter - Announcement of Karaoke Distributed to JOYSOUND","disabled":false,"id":147251,"url":"https://twitter.com/32ki_May/status/1791044005830238644"},{"category":"Commercial","description":"Spotify","disabled":false,"id":147455,"url":"https://open.spotify.com/track/5ic62hKqeDhZsa9l6YQxzJ?si=61350f89442148f2"},{"category":"Official","description":"\"it's over!\" (Illustration)","disabled":true,"id":147945,"url":"https://twitter.com/_CASTSTATION/status/1794171577778786502"},{"category":"Official","description":"\"24時間青空から紙吹雪が降ってくる世界観\" (Illustration)","disabled":true,"id":148404,"url":"https://twitter.com/_CASTSTATION/status/1794897112523768076"},{"category":"Reference","description":"Wikipedia (EN)","disabled":false,"id":148405,"url":"https://en.wikipedia.org/wiki/Mesmerizer_(song)"},{"category":"Reference","description":"Wikipedia (JP)","disabled":false,"id":148406,"url":"https://ja.wikipedia.org/wiki/%E3%83%A1%E3%82%BA%E3%83%9E%E3%83%A9%E3%82%A4%E3%82%B6%E3%83%BC"},{"category":"Official","description":"Twitter - Announcement of Karaoke Distributed to DAM","disabled":false,"id":148617,"url":"https://twitter.com/32ki_May/status/1798257358105395207"},{"category":"Reference","description":"UtaiteDB","disabled":false,"id":154999,"url":"https://utaitedb.net/S/63253"},{"category":"Reference","description":"Pixiv Encyclopedia","disabled":false,"id":155256,"url":"https://dic.pixiv.net/a/%E3%83%A1%E3%82%BA%E3%83%9E%E3%83%A9%E3%82%A4%E3%82%B6%E3%83%BC"},{"category":"Reference","description":"NicoNicoPedia","disabled":false,"id":155257,"url":"https://dic.nicovideo.jp/a/%E3%83%A1%E3%82%BA%E3%83%9E%E3%83%A9%E3%82%A4%E3%82%B6%E3%83%BC"},{"category":"Reference","description":"Moegirlpedia (zh-cn)","disabled":false,"id":155258,"url":"https://zh.moegirl.org.cn/%E5%82%AC%E7%9C%A0%E8%80%85"},{"category":"Reference","description":"MusicBrainz (Recording)","disabled":false,"id":156704,"url":"https://musicbrainz.org/recording/91e270ec-1561-49db-b9a1-f38ef28f22fb"},{"category":"Reference","description":"Project Sekai Wikia","disabled":false,"id":157001,"url":"https://projectsekai.fandom.com/wiki/Mesmerizer"},{"category":"Reference","description":"Namu Wiki","disabled":false,"id":157002,"url":"https://en.namu.wiki/w/%EB%A9%94%EC%8A%A4%EB%A8%B8%EB%9D%BC%EC%9D%B4%EC%A0%80#rfn-39"},{"category":"Official","description":"\"FOCUS TO\" (Illustration)","disabled":true,"id":161764,"url":"https://twitter.com/_CASTSTATION/status/1806546659335413901"},{"category":"Official","description":"\"強制解除\" (Illustration)","disabled":true,"id":161765,"url":"https://twitter.com/x_cast_x/status/1821841572893487453"},{"category":"Reference","description":"RemyWiki","disabled":false,"id":162381,"url":"https://remywiki.com/index.php?title=Mesmerizer"},{"category":"Reference","description":"Sekaipedia","disabled":false,"id":163859,"url":"https://www.sekaipedia.org/wiki/Mesmerizer"},{"category":"Other","description":"IMDB","disabled":false,"id":183118,"url":"https://www.imdb.com/title/tt33609125/"}],"cultureCodes":["ja"]}