{"additionalNames":"39みゅーじっく!, 39 Music!, 39뮤직!","artists":[{"artist":{"additionalNames":"みきとP, 愛島, Aijima, 미키토P","artistType":"Producer","deleted":false,"id":876,"name":"MikitoP","pictureMime":"image/jpeg","status":"Approved","version":30},"categories":"Producer","effectiveRoles":"Default","id":297855,"isCustomName":false,"isSupport":false,"name":"MikitoP","roles":"Default"},{"artist":{"additionalNames":"初音ミク, 初音未来, Chūyīn Wèilái, 하츠네 미쿠, 初音未來","artistType":"Vocaloid","deleted":false,"id":1,"name":"Hatsune Miku","pictureMime":"image/png","releaseDate":"2007-08-31T00:00:00Z","status":"Locked","version":39},"categories":"Vocalist","effectiveRoles":"Default","id":297856,"isCustomName":false,"isSupport":false,"name":"Hatsune Miku","roles":"Default"},{"artist":{"additionalNames":"平賀みえ, Hiraga Mie","artistType":"Animator","deleted":false,"id":2664,"name":"Not-116","pictureMime":"image/png","status":"Finished","version":10},"categories":"Animator","effectiveRoles":"Default","id":298797,"isCustomName":false,"isSupport":false,"name":"Not-116","roles":"Default"},{"artist":{"additionalNames":"まご","artistType":"Illustrator","deleted":false,"id":56910,"name":"mago","pictureMime":"image/jpeg","status":"Finished","version":4},"categories":"Illustrator","effectiveRoles":"Illustrator","id":355116,"isCustomName":false,"isSupport":false,"name":"mago","roles":"Default"},{"artist":{"additionalNames":"友達募集P, Tomodachi BoshuuP","artistType":"Producer","deleted":false,"id":2131,"name":"tomoboP","pictureMime":"image/png","status":"Finished","version":11},"categories":"Other","effectiveRoles":"Mixer","id":355117,"isCustomName":false,"isSupport":false,"name":"tomoboP","roles":"Mixer"},{"artist":{"additionalNames":"クリプトン・フューチャー・メディア, CFM, クリプトン・フューチャー・メディア（株）, Crypton Future Media, Inc., SONICWIRE, piapro","artistType":"Label","deleted":false,"id":25,"name":"Crypton Future Media","pictureMime":"image/gif","status":"Locked","version":30},"categories":"Label","effectiveRoles":"Default","id":1962704,"isCustomName":false,"isSupport":false,"name":"Crypton Future Media","roles":"Default"}],"artistString":"MikitoP feat. Hatsune Miku","createDate":"2016-06-24T05:54:27","defaultName":"39みゅーじっく!","defaultNameLanguage":"Japanese","favoritedTimes":153,"id":127519,"lengthSeconds":266,"mainPicture":{"urlOriginal":"https://i1.ytimg.com/vi/OuLZlZ18APQ/hqdefault.jpg","urlThumb":"https://i.ytimg.com/vi/OuLZlZ18APQ/default.jpg"},"maxMilliBpm":130000,"minMilliBpm":130000,"name":"Thank You Music!","names":[{"language":"Japanese","value":"39みゅーじっく!"},{"language":"English","value":"Thank You Music!"},{"language":"Romaji","value":"39 Music!"},{"language":"Unspecified","value":"39뮤직!"}],"publishDate":"2016-06-29T00:00:00Z","pvs":[{"author":"HatsuneMiku","disabled":false,"id":186183,"length":266,"name":"【初音ミク】39みゅーじっく！【オリジナルMV】","publishDate":"2016-06-29T00:00:00","pvId":"OuLZlZ18APQ","service":"Youtube","pvType":"Original","thumbUrl":"https://i.ytimg.com/vi/OuLZlZ18APQ/default.jpg","url":"https://youtu.be/OuLZlZ18APQ"},{"author":"みきとP","disabled":false,"id":186185,"length":265,"name":"39みゅーじっく！／初音ミク","publishDate":"2016-06-29T00:00:00","pvId":"sm29145868","service":"NicoNicoDouga","pvType":"Original","thumbUrl":"https://nicovideo.cdn.nimg.jp/thumbnails/29145868/29145868","url":"http://www.nicovideo.jp/watch/sm29145868"},{"author":"初音未来_Crypton","disabled":false,"extendedMetadata":{"json":"{\"Aid\":74840733,\"Bvid\":\"BV1yE411i7Ch\",\"Cid\":128023093}"},"id":698306,"length":267,"name":"【初音未来】39みゅーじっく！ / 39music!【MV】","publishDate":"2019-11-07T00:00:00","pvId":"74840733","service":"Bilibili","pvType":"Original","thumbUrl":"http://i1.hdslb.com/bfs/archive/315738cb4099eefcce1eadb94baf8de3f0e59139.jpg","url":"https://www.bilibili.com/video/av74840733"},{"author":"MikitoP - Topic","disabled":false,"id":1041571,"length":266,"name":"39みゅーじっく!","publishDate":"2020-04-14T00:00:00","pvId":"iAU1LmhtCSw","service":"Youtube","pvType":"Original","thumbUrl":"https://i.ytimg.com/vi/iAU1LmhtCSw/default.jpg","url":"https://youtu.be/iAU1LmhtCSw"}],"pvServices":"NicoNicoDouga, Youtube, Bilibili","ratingScore":823,"songType":"Original","status":"Approved","thumbUrl":"https://i.ytimg.com/vi/OuLZlZ18APQ/default.jpg","version":32,"webLinks":[{"category":"Official","description":"Piapro (instrumental w/o mastering)","disabled":false,"id":51851,"url":"http://piapro.jp/t/X1qd"},{"category":"Official","description":"Piapro (instrumental)","disabled":false,"id":51852,"url":"http://piapro.jp/t/xS2A"},{"category":"Reference","description":"MikuWiki","disabled":false,"id":63313,"url":"https://www5.atwiki.jp/hmiku/pages/34697.html"},{"category":"Reference","description":"Vocaloid Wiki","disabled":false,"id":63314,"url":"http://vocaloid.wikia.com/wiki/39%E3%81%BF%E3%82%85%E3%83%BC%E3%81%98%E3%81%A3%E3%81%8F%EF%BC%81_%2839_Music!%29"},{"category":"Reference","description":"Vocaloid Lyrics Wiki","disabled":false,"id":63315,"url":"https://vocaloidlyrics.miraheze.org/wiki/39%E3%81%BF%E3%82%85%E3%83%BC%E3%81%98%E3%81%A3%E3%81%8F%EF%BC%81_%2839_Music!%29"},{"category":"Commercial","description":"Spotify","disabled":false,"id":97929,"url":"https://open.spotify.com/track/7DZrnvfd78FMJgPYa8FSEy"},{"category":"Reference","description":"NicoNicoPedia","disabled":false,"id":109523,"url":"http://dic.nicovideo.jp/v/sm29145868"}],"cultureCodes":["ja"]}